{"version": 0.6, "generator": "Overpass API 0.7.57 93a4d346", "osm3s": {"timestamp_osm_base": "2022-04-19T07:46:40Z", "copyright": "The data included in this document is from www.openstreetmap.org. The data is made available under ODbL."}, "elements": [{"type": "node", "id": 38178162, "lat": 44.0637679, "lon": -121.1963229}, {"type": "node", "id": 38178164, "lat": 44.0644077, "lon": -121.1974679, "tags": {"highway": "turning_circle"}}, {"type": "node", "id": 38182176, "lat": 43.9683378, "lon": -121.272123}, {"type": "node", "id": 38195468, "lat": 43.9488449, "lon": -121.2230965}, {"type": "node", "id": 38202103, "lat": 44.0377708, "lon": -121.1535447}, {"type": "node", "id": 38209220, "lat": 43.9877081, "lon": -121.2198144}, {"type": "node", "id": 38209249, "lat": 43.993209, "lon": -121.2189526}, {"type": "node", "id": 38209256, "lat": 43.9877451, "lon": -121.216378}, {"type": "node", "id": 38209259, "lat": 43.9875698, "lon": -121.2167575}, {"type": "node", "id": 38209261, "lat": 43.9874922, "lon": -121.2170397}, {"type": "node", "id": 38209265, "lat": 43.9874543, "lon": -121.2180869}, {"type": "node", "id": 38209269, "lat": 43.9875615, "lon": -121.2187682}, {"type": "node", "id": 38209274, "lat": 43.9876769, "lon": -121.2201948}, {"type": "node", "id": 38209277, "lat": 43.9876673, "lon": -121.2205963}, {"type": "node", "id": 38209435, "lat": 43.983848, "lon": -121.2078051}, {"type": "node", "id": 38216948, "lat": 44.0078119, "lon": -121.1862438}, {"type": "node", "id": 38222323, "lat": 43.9931662, "lon": -121.2336141}, {"type": "node", "id": 38222332, "lat": 43.9931737, "lon": -121.2290894}, {"type": "node", "id": 38224504, "lat": 44.0512086, "lon": -121.1766726}, {"type": "node", "id": 38224600, "lat": 44.0659964, "lon": -121.1716037}, {"type": "node", "id": 38227565, "lat": 43.9768503, "lon": -121.2014736}, {"type": "node", "id": 38227571, "lat": 43.9765536, "lon": -121.2011213}, {"type": "node", "id": 38239211, "lat": 43.9772878, "lon": -121.2062913}, {"type": "node", "id": 38239257, "lat": 43.9761401, "lon": -121.215683}, {"type": "node", "id": 38239270, "lat": 43.9771996, "lon": -121.217374}, {"type": "node", "id": 38239533, "lat": 44.1329165, "lon": -121.1567846}, {"type": "node", "id": 38239582, "lat": 44.129605, "lon": -121.1618393}, {"type": "node", "id": 38241368, "lat": 43.9663276, "lon": -121.2687338}, {"type": "node", "id": 38242540, "lat": 43.9418606, "lon": -121.2053201}, {"type": "node", "id": 38243053, "lat": 43.9379656, "lon": -121.1993201}, {"type": "node", "id": 38245922, "lat": 44.0838298, "lon": -121.1983289}, {"type": "node", "id": 38246097, "lat": 44.065676, "lon": -121.1985043}, {"type": "node", "id": 38262933, "lat": 44.1191025, "lon": -121.2048136}, {"type": "node", "id": 38270336, "lat": 43.9484186, "lon": -121.2440749}, {"type": "node", "id": 38270437, "lat": 43.9456988, "lon": -121.2311053}, {"type": "node", "id": 38278043, "lat": 44.0946213, "lon": -121.2034017}, {"type": "node", "id": 38279196, "lat": 44.0730548, "lon": -121.1139358}, {"type": "node", "id": 38282111, "lat": 44.0077517, "lon": -121.1808907}, {"type": "node", "id": 38287399, "lat": 44.0375147, "lon": -121.1531923}, {"type": "node", "id": 38290589, "lat": 44.0946624, "lon": -121.1822458}, {"type": "node", "id": 38290590, "lat": 44.0946361, "lon": -121.1833413}, {"type": "node", "id": 38291959, "lat": 43.986812, "lon": -121.2096258}, {"type": "node", "id": 38293229, "lat": 44.0511618, "lon": -121.2133214}, {"type": "node", "id": 38296690, "lat": 44.007781, "lon": -121.1973593}, {"type": "node", "id": 38296924, "lat": 44.0240288, "lon": -121.2238405}, {"type": "node", "id": 38298782, "lat": 43.9973273, "lon": -121.2440116}, {"type": "node", "id": 38300200, "lat": 44.0076721, "lon": -121.2037299}, {"type": "node", "id": 38302853, "lat": 43.9462476, "lon": -121.2383547}, {"type": "node", "id": 38306796, "lat": 44.0511988, "lon": -121.1681036}, {"type": "node", "id": 38308105, "lat": 44.10397, "lon": -121.1933496}, {"type": "node", "id": 38308107, "lat": 44.1049731, "lon": -121.192659}, {"type": "node", "id": 38311164, "lat": 43.9429546, "lon": -121.207693}, {"type": "node", "id": 38312789, "lat": 44.0564165, "lon": -121.2120102}, {"type": "node", "id": 38312889, "lat": 44.0873713, "lon": -121.1938695}, {"type": "node", "id": 38312890, "lat": 44.0948038, "lon": -121.193959}, {"type": "node", "id": 38316428, "lat": 44.0153489, "lon": -121.2089952}, {"type": "node", "id": 38316471, "lat": 44.0147842, "lon": -121.2010608}, {"type": "node", "id": 38335324, "lat": 43.9779341, "lon": -121.3009552}, {"type": "node", "id": 38335401, "lat": 43.9751328, "lon": -121.3004196}, {"type": "node", "id": 38351849, "lat": 44.0077185, "lon": -121.1635981}, {"type": "node", "id": 38354239, "lat": 44.0579538, "lon": -121.2206644}, {"type": "node", "id": 38366006, "lat": 43.9475847, "lon": -121.2191747}, {"type": "node", "id": 38374826, "lat": 44.0712724, "lon": -121.1234478}, {"type": "node", "id": 38374916, "lat": 44.0737882, "lon": -121.1459233}, {"type": "node", "id": 38375555, "lat": 43.9460371, "lon": -121.2154013}, {"type": "node", "id": 38384154, "lat": 43.9380125, "lon": -121.1994431}, {"type": "node", "id": 38384199, "lat": 43.938123, "lon": -121.1997386}, {"type": "node", "id": 38386547, "lat": 44.049241, "lon": -121.1902802}, {"type": "node", "id": 38394986, "lat": 44.0657838, "lon": -121.1833771}, {"type": "node", "id": 38397123, "lat": 43.9689679, "lon": -121.2756972}, {"type": "node", "id": 38398650, "lat": 44.129307, "lon": -121.162232}, {"type": "node", "id": 38464467, "lat": 44.038669, "lon": -121.2034693}, {"type": "node", "id": 38464476, "lat": 44.0405072, "lon": -121.1592825}, {"type": "node", "id": 38465607, "lat": 44.0098635, "lon": -121.2593048}, {"type": "node", "id": 38466165, "lat": 44.0621734, "lon": -121.1934191}, {"type": "node", "id": 38466167, "lat": 44.0621345, "lon": -121.1936977}, {"type": "node", "id": 38466169, "lat": 44.0616493, "lon": -121.1943696}, {"type": "node", "id": 38466171, "lat": 44.0615678, "lon": -121.1947413}, {"type": "node", "id": 38466173, "lat": 44.0616205, "lon": -121.1952604}, {"type": "node", "id": 38466175, "lat": 44.0616015, "lon": -121.1957277}, {"type": "node", "id": 38466176, "lat": 44.061382, "lon": -121.1962744}, {"type": "node", "id": 38466179, "lat": 44.0611782, "lon": -121.1967371}, {"type": "node", "id": 38466181, "lat": 44.0612105, "lon": -121.1971884}, {"type": "node", "id": 38471235, "lat": 44.0221149, "lon": -121.2185418}, {"type": "node", "id": 38471925, "lat": 43.9748622, "lon": -121.2011017}, {"type": "node", "id": 38473195, "lat": 43.9763459, "lon": -121.2144409}, {"type": "node", "id": 38473196, "lat": 43.9776808, "lon": -121.214734}, {"type": "node", "id": 38473198, "lat": 43.9778741, "lon": -121.2147511}, {"type": "node", "id": 38473200, "lat": 43.9796675, "lon": -121.2132809}, {"type": "node", "id": 38473202, "lat": 43.9807575, "lon": -121.2127653}, {"type": "node", "id": 38473204, "lat": 43.9820537, "lon": -121.2120654}, {"type": "node", "id": 38473206, "lat": 43.9834167, "lon": -121.2119829}, {"type": "node", "id": 38473208, "lat": 43.9841164, "lon": -121.2123681}, {"type": "node", "id": 38473209, "lat": 43.9847566, "lon": -121.2128773}, {"type": "node", "id": 38474846, "lat": 44.0656189, "lon": -121.2010652}, {"type": "node", "id": 38478064, "lat": 43.9845739, "lon": -121.2200052}, {"type": "node", "id": 38478067, "lat": 43.980691, "lon": -121.2204632}, {"type": "node", "id": 38478073, "lat": 43.9844779, "lon": -121.2178139}, {"type": "node", "id": 38478075, "lat": 43.9842274, "lon": -121.2159099}, {"type": "node", "id": 38478077, "lat": 43.9845411, "lon": -121.214848}, {"type": "node", "id": 38478079, "lat": 43.9845873, "lon": -121.2135385}, {"type": "node", "id": 38478084, "lat": 43.9856449, "lon": -121.2115178}, {"type": "node", "id": 38478086, "lat": 43.9862077, "lon": -121.2103966}, {"type": "node", "id": 38479644, "lat": 43.9969448, "lon": -121.2416692}, {"type": "node", "id": 38481572, "lat": 44.1233294, "lon": -121.1701039}, {"type": "node", "id": 38482972, "lat": 44.108191, "lon": -121.1819695, "tags": {"highway": "turning_circle"}}, {"type": "node", "id": 38485180, "lat": 44.1064157, "lon": -121.1782411}, {"type": "node", "id": 38487096, "lat": 43.9933134, "lon": -121.1940461}, {"type": "node", "id": 38489396, "lat": 44.050966, "lon": -121.153293}, {"type": "node", "id": 38489397, "lat": 44.0511461, "lon": -121.1538687}, {"type": "node", "id": 38489398, "lat": 44.0511595, "lon": -121.1544859}, {"type": "node", "id": 38489399, "lat": 44.0512086, "lon": -121.1632869}, {"type": "node", "id": 38489400, "lat": 44.0512282, "lon": -121.1807524}, {"type": "node", "id": 38489401, "lat": 44.0512105, "lon": -121.1866838}, {"type": "node", "id": 38489405, "lat": 44.0511884, "lon": -121.1933768}, {"type": "node", "id": 38489407, "lat": 44.051508, "lon": -121.1979298}, {"type": "node", "id": 38489410, "lat": 44.0511735, "lon": -121.198461}, {"type": "node", "id": 38489413, "lat": 44.0511478, "lon": -121.2034973}, {"type": "node", "id": 38489421, "lat": 44.0511716, "lon": -121.2234965}, {"type": "node", "id": 38489425, "lat": 44.0512409, "lon": -121.2343921}, {"type": "node", "id": 38494141, "lat": 44.0578198, "lon": -121.2234637}, {"type": "node", "id": 38494173, "lat": 44.080165, "lon": -121.203483}, {"type": "node", "id": 38495058, "lat": 44.0395798, "lon": -121.1563484}, {"type": "node", "id": 38495060, "lat": 44.0399566, "lon": -121.1574148}, {"type": "node", "id": 38495067, "lat": 44.0430826, "lon": -121.1679021}, {"type": "node", "id": 38495070, "lat": 44.0439491, "lon": -121.1709161}, {"type": "node", "id": 38495072, "lat": 44.0447629, "lon": -121.1748634}, {"type": "node", "id": 38495075, "lat": 44.0450379, "lon": -121.1760664}, {"type": "node", "id": 38495080, "lat": 44.0459569, "lon": -121.1792405}, {"type": "node", "id": 38495083, "lat": 44.0501721, "lon": -121.1933915}, {"type": "node", "id": 38495086, "lat": 44.053493, "lon": -121.204584}, {"type": "node", "id": 38495088, "lat": 44.0546458, "lon": -121.2077223}, {"type": "node", "id": 38495091, "lat": 44.0560006, "lon": -121.2110533}, {"type": "node", "id": 38495093, "lat": 44.0567815, "lon": -121.2131112}, {"type": "node", "id": 38495096, "lat": 44.057753, "lon": -121.2181243}, {"type": "node", "id": 38495099, "lat": 44.0578749, "lon": -121.2191809}, {"type": "node", "id": 38495102, "lat": 44.0579492, "lon": -121.2219548}, {"type": "node", "id": 38495105, "lat": 44.0567335, "lon": -121.2324366}, {"type": "node", "id": 38495109, "lat": 44.055347, "lon": -121.2434447}, {"type": "node", "id": 38495111, "lat": 44.0549182, "lon": -121.247029}, {"type": "node", "id": 38495113, "lat": 44.0548752, "lon": -121.247987}, {"type": "node", "id": 38499492, "lat": 43.9560394, "lon": -121.2634508}, {"type": "node", "id": 38500327, "lat": 43.9511284, "lon": -121.2512633}, {"type": "node", "id": 38502803, "lat": 44.059333, "lon": -121.193393}, {"type": "node", "id": 38502813, "lat": 44.0656396, "lon": -121.1934566}, {"type": "node", "id": 38505642, "lat": 44.0007852, "lon": -121.2439772}, {"type": "node", "id": 38505645, "lat": 43.9969041, "lon": -121.2398673}, {"type": "node", "id": 38505650, "lat": 43.9937218, "lon": -121.2391439}, {"type": "node", "id": 38505652, "lat": 43.9932211, "lon": -121.2366758}, {"type": "node", "id": 38505661, "lat": 43.9931908, "lon": -121.2242201}, {"type": "node", "id": 38505667, "lat": 43.9932183, "lon": -121.2129689}, {"type": "node", "id": 38507650, "lat": 44.094619, "lon": -121.1651029}, {"type": "node", "id": 38507651, "lat": 44.09459, "lon": -121.170745}, {"type": "node", "id": 38507654, "lat": 44.0945889, "lon": -121.1732128}, {"type": "node", "id": 38507656, "lat": 44.0945879, "lon": -121.178244}, {"type": "node", "id": 38507660, "lat": 44.0947126, "lon": -121.1825022}, {"type": "node", "id": 38507663, "lat": 44.0951251, "lon": -121.1833388}, {"type": "node", "id": 38507667, "lat": 44.097332, "lon": -121.1858755}, {"type": "node", "id": 38507669, "lat": 44.0983574, "lon": -121.1870711}, {"type": "node", "id": 38507670, "lat": 44.1005956, "lon": -121.1896357}, {"type": "node", "id": 38507672, "lat": 44.103239, "lon": -121.1926596}, {"type": "node", "id": 38507674, "lat": 44.1042555, "lon": -121.1935303}, {"type": "node", "id": 38507675, "lat": 44.1045538, "lon": -121.1937254}, {"type": "node", "id": 38507676, "lat": 44.1047599, "lon": -121.1938436}, {"type": "node", "id": 38507677, "lat": 44.1051469, "lon": -121.193958}, {"type": "node", "id": 38507678, "lat": 44.1057194, "lon": -121.1941593}, {"type": "node", "id": 38507679, "lat": 44.1063391, "lon": -121.1944832}, {"type": "node", "id": 38507680, "lat": 44.1067781, "lon": -121.19488}, {"type": "node", "id": 38507683, "lat": 44.1073891, "lon": -121.1956403}, {"type": "node", "id": 38507685, "lat": 44.1084645, "lon": -121.1968839}, {"type": "node", "id": 38507687, "lat": 44.1088262, "lon": -121.1972492}, {"type": "node", "id": 38507689, "lat": 44.1094555, "lon": -121.1977461}, {"type": "node", "id": 38507691, "lat": 44.1106469, "lon": -121.1986623}, {"type": "node", "id": 38507692, "lat": 44.111033, "lon": -121.1989739}, {"type": "node", "id": 38507693, "lat": 44.111407, "lon": -121.1993931}, {"type": "node", "id": 38507695, "lat": 44.1127683, "lon": -121.2012851}, {"type": "node", "id": 38507697, "lat": 44.1132177, "lon": -121.2019065}, {"type": "node", "id": 38507699, "lat": 44.1137045, "lon": -121.2023627}, {"type": "node", "id": 38507701, "lat": 44.1156988, "lon": -121.2029647}, {"type": "node", "id": 38507703, "lat": 44.1170574, "lon": -121.203199}, {"type": "node", "id": 38509602, "lat": 44.0077722, "lon": -121.2339848}, {"type": "node", "id": 38517749, "lat": 44.0946319, "lon": -121.1921959}, {"type": "node", "id": 38518143, "lat": 44.00772, "lon": -121.1650153}, {"type": "node", "id": 38518144, "lat": 44.0077037, "lon": -121.1655649}, {"type": "node", "id": 38518146, "lat": 44.0077209, "lon": -121.1662364}, {"type": "node", "id": 38518148, "lat": 44.0077403, "lon": -121.1702921}, {"type": "node", "id": 38518151, "lat": 44.0077403, "lon": -121.1737126}, {"type": "node", "id": 38518156, "lat": 44.0077913, "lon": -121.1826756}, {"type": "node", "id": 38518158, "lat": 44.00818, "lon": -121.1845278}, {"type": "node", "id": 38518165, "lat": 44.00778, "lon": -121.1864712}, {"type": "node", "id": 38518166, "lat": 44.0077984, "lon": -121.1885771}, {"type": "node", "id": 38518168, "lat": 44.0078349, "lon": -121.1935732}, {"type": "node", "id": 38518170, "lat": 44.0076776, "lon": -121.2069983}, {"type": "node", "id": 38518172, "lat": 44.0076503, "lon": -121.2149613}, {"type": "node", "id": 38518179, "lat": 44.0076464, "lon": -121.2240647}, {"type": "node", "id": 38518197, "lat": 44.0077819, "lon": -121.2437336}, {"type": "node", "id": 38518204, "lat": 44.0078287, "lon": -121.2478177}, {"type": "node", "id": 38518211, "lat": 44.0078694, "lon": -121.2511821}, {"type": "node", "id": 38518213, "lat": 44.0078857, "lon": -121.2516513}, {"type": "node", "id": 38518215, "lat": 44.0079163, "lon": -121.252051}, {"type": "node", "id": 38518217, "lat": 44.0082902, "lon": -121.2550743}, {"type": "node", "id": 38518219, "lat": 44.0086379, "lon": -121.2564607}, {"type": "node", "id": 38518221, "lat": 44.0092185, "lon": -121.2575717}, {"type": "node", "id": 38518223, "lat": 44.009398, "lon": -121.2579272}, {"type": "node", "id": 38518225, "lat": 44.0095378, "lon": -121.2582367}, {"type": "node", "id": 38518723, "lat": 44.0472724, "lon": -121.2035079}, {"type": "node", "id": 38518727, "lat": 44.0494986, "lon": -121.2036056}, {"type": "node", "id": 38521841, "lat": 44.1045528, "lon": -121.1821405, "tags": {"highway": "turning_circle"}}, {"type": "node", "id": 38521842, "lat": 44.1045556, "lon": -121.17823}, {"type": "node", "id": 38522502, "lat": 43.9809605, "lon": -121.2160605}, {"type": "node", "id": 38522503, "lat": 43.9814072, "lon": -121.2162313}, {"type": "node", "id": 38522504, "lat": 43.9820509, "lon": -121.2164814}, {"type": "node", "id": 38522505, "lat": 43.982556, "lon": -121.216595}, {"type": "node", "id": 38522962, "lat": 44.0655202, "lon": -121.163236}, {"type": "node", "id": 38526657, "lat": 43.9770083, "lon": -121.2044898}, {"type": "node", "id": 38526659, "lat": 43.9783346, "lon": -121.2052061}, {"type": "node", "id": 38526662, "lat": 43.979391, "lon": -121.205776}, {"type": "node", "id": 38526664, "lat": 43.9801499, "lon": -121.2062204}, {"type": "node", "id": 38526666, "lat": 43.9808298, "lon": -121.2065323}, {"type": "node", "id": 38526668, "lat": 43.9816151, "lon": -121.2066721}, {"type": "node", "id": 38526672, "lat": 43.982639, "lon": -121.2074623}, {"type": "node", "id": 38526675, "lat": 43.9833816, "lon": -121.2074573}, {"type": "node", "id": 38526681, "lat": 43.9844767, "lon": -121.2083211}, {"type": "node", "id": 38526683, "lat": 43.9847011, "lon": -121.2083668}, {"type": "node", "id": 38526685, "lat": 43.9851218, "lon": -121.2079791}, {"type": "node", "id": 38526687, "lat": 43.9856021, "lon": -121.2079519}, {"type": "node", "id": 38526689, "lat": 43.9862423, "lon": -121.2085482}, {"type": "node", "id": 38528451, "lat": 43.9583622, "lon": -121.2673968}, {"type": "node", "id": 38531980, "lat": 43.9764949, "lon": -121.2103581}, {"type": "node", "id": 38533401, "lat": 44.015184, "lon": -121.1934004}, {"type": "node", "id": 38533410, "lat": 44.0222356, "lon": -121.1931255}, {"type": "node", "id": 38534324, "lat": 43.9793537, "lon": -121.2064814}, {"type": "node", "id": 38534325, "lat": 43.9794179, "lon": -121.2066436}, {"type": "node", "id": 38534328, "lat": 43.9804552, "lon": -121.2083577}, {"type": "node", "id": 38534332, "lat": 43.9803421, "lon": -121.2092107}, {"type": "node", "id": 38534334, "lat": 43.9797108, "lon": -121.2100004}, {"type": "node", "id": 38534337, "lat": 43.9797026, "lon": -121.2102355}, {"type": "node", "id": 38534341, "lat": 43.9799616, "lon": -121.211168}, {"type": "node", "id": 38534345, "lat": 43.981104, "lon": -121.2136669}, {"type": "node", "id": 38534348, "lat": 43.9812347, "lon": -121.2144648}, {"type": "node", "id": 38534352, "lat": 43.9811904, "lon": -121.215321}, {"type": "node", "id": 38534357, "lat": 43.9807925, "lon": -121.2164124}, {"type": "node", "id": 38534361, "lat": 43.9806583, "lon": -121.2169767}, {"type": "node", "id": 38534364, "lat": 43.9804996, "lon": -121.2185432}, {"type": "node", "id": 38534365, "lat": 43.9807225, "lon": -121.2195859}, {"type": "node", "id": 38534369, "lat": 43.9799707, "lon": -121.2224352}, {"type": "node", "id": 38534372, "lat": 43.9799907, "lon": -121.2242922}, {"type": "node", "id": 38543338, "lat": 43.9851059, "lon": -121.2180857}, {"type": "node", "id": 38543756, "lat": 44.1082045, "lon": -121.1782517}, {"type": "node", "id": 38545423, "lat": 43.9662914, "lon": -121.19594}, {"type": "node", "id": 38545424, "lat": 43.968337, "lon": -121.195948}, {"type": "node", "id": 38545427, "lat": 43.9705931, "lon": -121.1960015}, {"type": "node", "id": 38545430, "lat": 43.9712123, "lon": -121.1958141}, {"type": "node", "id": 38545432, "lat": 43.9715256, "lon": -121.1956688}, {"type": "node", "id": 38545434, "lat": 43.9726753, "lon": -121.1960834}, {"type": "node", "id": 38545437, "lat": 43.9731035, "lon": -121.1961791}, {"type": "node", "id": 38545439, "lat": 43.9736901, "lon": -121.1963458}, {"type": "node", "id": 38545441, "lat": 43.9738399, "lon": -121.1967727}, {"type": "node", "id": 38545443, "lat": 43.9733763, "lon": -121.1999516}, {"type": "node", "id": 38545445, "lat": 43.9738633, "lon": -121.2003819}, {"type": "node", "id": 38545447, "lat": 43.9743419, "lon": -121.2007529}, {"type": "node", "id": 38545449, "lat": 43.9747544, "lon": -121.2010277}, {"type": "node", "id": 38545452, "lat": 43.9767204, "lon": -121.2011511}, {"type": "node", "id": 38545453, "lat": 43.9768133, "lon": -121.2012692}, {"type": "node", "id": 38545454, "lat": 43.9768694, "lon": -121.2034731}, {"type": "node", "id": 38545455, "lat": 43.9769539, "lon": -121.2040274}, {"type": "node", "id": 38545456, "lat": 43.9772349, "lon": -121.2057814}, {"type": "node", "id": 38545458, "lat": 43.9773165, "lon": -121.2067736}, {"type": "node", "id": 38545460, "lat": 43.9772518, "lon": -121.2072043}, {"type": "node", "id": 38545461, "lat": 43.977072, "lon": -121.2078963}, {"type": "node", "id": 38545462, "lat": 43.9768724, "lon": -121.2085525}, {"type": "node", "id": 38545463, "lat": 43.9765386, "lon": -121.2094291}, {"type": "node", "id": 38545464, "lat": 43.9766754, "lon": -121.2122965}, {"type": "node", "id": 38545465, "lat": 43.9766681, "lon": -121.2127929}, {"type": "node", "id": 38545466, "lat": 43.9766329, "lon": -121.2131485}, {"type": "node", "id": 38545467, "lat": 43.9761148, "lon": -121.2163125}, {"type": "node", "id": 38545468, "lat": 43.976157, "lon": -121.2168211}, {"type": "node", "id": 38545469, "lat": 43.9761944, "lon": -121.217226}, {"type": "node", "id": 38545470, "lat": 43.9762807, "lon": -121.217359}, {"type": "node", "id": 38545471, "lat": 43.9799348, "lon": -121.2171296}, {"type": "node", "id": 38545956, "lat": 44.131432, "lon": -121.159247}, {"type": "node", "id": 38545957, "lat": 44.1296945, "lon": -121.161731}, {"type": "node", "id": 38545958, "lat": 44.1290205, "lon": -121.1626496}, {"type": "node", "id": 38545959, "lat": 44.124841, "lon": -121.16812}, {"type": "node", "id": 38545964, "lat": 44.105912, "lon": -121.191176}, {"type": "node", "id": 38545965, "lat": 44.1047497, "lon": -121.1963137}, {"type": "node", "id": 38545966, "lat": 44.1047361, "lon": -121.1983229}, {"type": "node", "id": 38545967, "lat": 44.1044865, "lon": -121.1998314}, {"type": "node", "id": 38545968, "lat": 44.1040657, "lon": -121.2009464}, {"type": "node", "id": 38545969, "lat": 44.1034889, "lon": -121.2018901}, {"type": "node", "id": 38545970, "lat": 44.102894, "lon": -121.202503}, {"type": "node", "id": 38545971, "lat": 44.1019148, "lon": -121.2031672}, {"type": "node", "id": 38545973, "lat": 44.1010518, "lon": -121.2033561}, {"type": "node", "id": 38545975, "lat": 44.1003406, "lon": -121.203393}, {"type": "node", "id": 38545984, "lat": 44.0685541, "lon": -121.2036373}, {"type": "node", "id": 38549081, "lat": 44.0229836, "lon": -121.2230765}, {"type": "node", "id": 38550194, "lat": 44.1063686, "lon": -121.181981, "tags": {"highway": "turning_circle"}}, {"type": "node", "id": 38552096, "lat": 43.9537842, "lon": -121.2582645}, {"type": "node", "id": 38552799, "lat": 43.9601121, "lon": -121.2680256}, {"type": "node", "id": 38552801, "lat": 43.9608368, "lon": -121.2681631}, {"type": "node", "id": 38552804, "lat": 43.9650305, "lon": -121.2684722}, {"type": "node", "id": 38552807, "lat": 43.96752, "lon": -121.2694129}, {"type": "node", "id": 38552808, "lat": 43.9677787, "lon": -121.2697247}, {"type": "node", "id": 38552811, "lat": 43.968146, "lon": -121.2704693}, {"type": "node", "id": 38552812, "lat": 43.968334, "lon": -121.2714664}, {"type": "node", "id": 38552817, "lat": 43.9686351, "lon": -121.2747087}, {"type": "node", "id": 38552819, "lat": 43.9688706, "lon": -121.2754092}, {"type": "node", "id": 38552822, "lat": 43.9692491, "lon": -121.2765688}, {"type": "node", "id": 38552826, "lat": 43.9694519, "lon": -121.2773778}, {"type": "node", "id": 38552827, "lat": 43.9694156, "lon": -121.281359}, {"type": "node", "id": 38552829, "lat": 43.9701508, "lon": -121.2878694}, {"type": "node", "id": 38552835, "lat": 43.9706162, "lon": -121.296192}, {"type": "node", "id": 38552836, "lat": 43.9707633, "lon": -121.2972668}, {"type": "node", "id": 38552838, "lat": 43.9711217, "lon": -121.2982554}, {"type": "node", "id": 38552840, "lat": 43.971584, "lon": -121.2989978}, {"type": "node", "id": 38552842, "lat": 43.9723155, "lon": -121.2996761}, {"type": "node", "id": 38552843, "lat": 43.9734412, "lon": -121.3000974}, {"type": "node", "id": 38552850, "lat": 43.9787665, "lon": -121.3011288}, {"type": "node", "id": 38552853, "lat": 43.9828193, "lon": -121.301928}, {"type": "node", "id": 38552856, "lat": 43.9831778, "lon": -121.3020923}, {"type": "node", "id": 38552858, "lat": 43.9844042, "lon": -121.30275}, {"type": "node", "id": 38553299, "lat": 44.0222161, "lon": -121.1934268}, {"type": "node", "id": 38553301, "lat": 44.0216236, "lon": -121.1967801}, {"type": "node", "id": 38553304, "lat": 44.0216849, "lon": -121.2007103}, {"type": "node", "id": 38553306, "lat": 44.0221287, "lon": -121.2037}, {"type": "node", "id": 38553308, "lat": 44.0221878, "lon": -121.2069744}, {"type": "node", "id": 38553309, "lat": 44.0221389, "lon": -121.2084397}, {"type": "node", "id": 38553316, "lat": 44.022123, "lon": -121.2131024}, {"type": "node", "id": 38553318, "lat": 44.0220952, "lon": -121.2154697}, {"type": "node", "id": 38553320, "lat": 44.0223216, "lon": -121.2209524}, {"type": "node", "id": 38553321, "lat": 44.022539, "lon": -121.2222898}, {"type": "node", "id": 38553322, "lat": 44.0227112, "lon": -121.2226637}, {"type": "node", "id": 38553323, "lat": 44.0233258, "lon": -121.223411}, {"type": "node", "id": 38553326, "lat": 44.0237114, "lon": -121.2237417}, {"type": "node", "id": 38553328, "lat": 44.0289699, "lon": -121.2238341}, {"type": "node", "id": 38556745, "lat": 44.0658422, "lon": -121.173331}, {"type": "node", "id": 38556777, "lat": 44.0873854, "lon": -121.173313}, {"type": "node", "id": 38574493, "lat": 44.0684797, "lon": -121.1598729}, {"type": "node", "id": 38580161, "lat": 44.074866, "lon": -121.0894831}, {"type": "node", "id": 38580163, "lat": 44.0748499, "lon": -121.0905044}, {"type": "node", "id": 38580165, "lat": 44.0745641, "lon": -121.0914923}, {"type": "node", "id": 38580167, "lat": 44.0731527, "lon": -121.0962416}, {"type": "node", "id": 38580168, "lat": 44.0729327, "lon": -121.0980519}, {"type": "node", "id": 38580170, "lat": 44.0730162, "lon": -121.1014474}, {"type": "node", "id": 38580171, "lat": 44.0726726, "lon": -121.1032192}, {"type": "node", "id": 38580175, "lat": 44.0718376, "lon": -121.106661}, {"type": "node", "id": 38580177, "lat": 44.0717638, "lon": -121.1073449}, {"type": "node", "id": 38580179, "lat": 44.0718058, "lon": -121.1079727}, {"type": "node", "id": 38580181, "lat": 44.0719356, "lon": -121.1086032}, {"type": "node", "id": 38580183, "lat": 44.0725024, "lon": -121.1105655}, {"type": "node", "id": 38580185, "lat": 44.0730195, "lon": -121.1124361}, {"type": "node", "id": 38580189, "lat": 44.0730098, "lon": -121.114575}, {"type": "node", "id": 38580190, "lat": 44.0728306, "lon": -121.1154413}, {"type": "node", "id": 38580192, "lat": 44.0717702, "lon": -121.1198115}, {"type": "node", "id": 38580194, "lat": 44.0717349, "lon": -121.1210877}, {"type": "node", "id": 38580196, "lat": 44.0711775, "lon": -121.1242632}, {"type": "node", "id": 38580197, "lat": 44.0712112, "lon": -121.1251326}, {"type": "node", "id": 38580198, "lat": 44.0712975, "lon": -121.1257851}, {"type": "node", "id": 38580199, "lat": 44.0713991, "lon": -121.1262791}, {"type": "node", "id": 38580200, "lat": 44.0716767, "lon": -121.127189}, {"type": "node", "id": 38580202, "lat": 44.0724059, "lon": -121.1292695}, {"type": "node", "id": 38580203, "lat": 44.0731317, "lon": -121.1317056}, {"type": "node", "id": 38580205, "lat": 44.0737868, "lon": -121.1380127}, {"type": "node", "id": 38580207, "lat": 44.0737836, "lon": -121.1465301}, {"type": "node", "id": 38580209, "lat": 44.0737547, "lon": -121.1512973}, {"type": "node", "id": 38580211, "lat": 44.0731911, "lon": -121.1524483}, {"type": "node", "id": 38580213, "lat": 44.0719531, "lon": -121.1546766}, {"type": "node", "id": 38580215, "lat": 44.0708563, "lon": -121.1563796}, {"type": "node", "id": 38580217, "lat": 44.0695605, "lon": -121.158333}, {"type": "node", "id": 38580219, "lat": 44.0689069, "lon": -121.159294}, {"type": "node", "id": 38580221, "lat": 44.0680923, "lon": -121.1602686}, {"type": "node", "id": 38580223, "lat": 44.0657289, "lon": -121.1623202}, {"type": "node", "id": 38580225, "lat": 44.0656534, "lon": -121.1625124}, {"type": "node", "id": 38580228, "lat": 44.0655, "lon": -121.1637838}, {"type": "node", "id": 38580230, "lat": 44.0660893, "lon": -121.1670978}, {"type": "node", "id": 38580232, "lat": 44.0662926, "lon": -121.1685169}, {"type": "node", "id": 38580235, "lat": 44.0658213, "lon": -121.1746756}, {"type": "node", "id": 38580238, "lat": 44.0657134, "lon": -121.1898518}, {"type": "node", "id": 38580240, "lat": 44.0656669, "lon": -121.1950749}, {"type": "node", "id": 38582037, "lat": 44.015151, "lon": -121.1956738}, {"type": "node", "id": 38582041, "lat": 44.0148769, "lon": -121.1991844}, {"type": "node", "id": 38582043, "lat": 44.014527, "lon": -121.199643}, {"type": "node", "id": 38582046, "lat": 44.014322, "lon": -121.2008103}, {"type": "node", "id": 38582059, "lat": 44.015017, "lon": -121.2088267}, {"type": "node", "id": 38583629, "lat": 44.0186848, "lon": -121.2085962}, {"type": "node", "id": 38583632, "lat": 44.0166032, "lon": -121.2091367}, {"type": "node", "id": 38583726, "lat": 43.9551543, "lon": -121.261536}, {"type": "node", "id": 38583729, "lat": 43.9575766, "lon": -121.2665618}, {"type": "node", "id": 38584201, "lat": 43.9387722, "lon": -121.201279}, {"type": "node", "id": 38584203, "lat": 43.9395539, "lon": -121.20204}, {"type": "node", "id": 38584205, "lat": 43.9402674, "lon": -121.2024485}, {"type": "node", "id": 38584207, "lat": 43.9406177, "lon": -121.2027523}, {"type": "node", "id": 38584209, "lat": 43.9411871, "lon": -121.2037379}, {"type": "node", "id": 38584211, "lat": 43.9418118, "lon": -121.2051625}, {"type": "node", "id": 38584228, "lat": 43.9419439, "lon": -121.2055402}, {"type": "node", "id": 38584230, "lat": 43.9425064, "lon": -121.207065}, {"type": "node", "id": 38584232, "lat": 43.9427702, "lon": -121.2074624}, {"type": "node", "id": 38584236, "lat": 43.9438203, "lon": -121.2087985}, {"type": "node", "id": 38584238, "lat": 43.9441169, "lon": -121.2095249}, {"type": "node", "id": 38584241, "lat": 43.9462757, "lon": -121.2161432}, {"type": "node", "id": 38584242, "lat": 43.9468459, "lon": -121.217774}, {"type": "node", "id": 38584244, "lat": 43.9478905, "lon": -121.2197307}, {"type": "node", "id": 38584246, "lat": 43.9483292, "lon": -121.2205997}, {"type": "node", "id": 38584248, "lat": 43.948716, "lon": -121.221833}, {"type": "node", "id": 38584250, "lat": 43.9488302, "lon": -121.2237817}, {"type": "node", "id": 38584252, "lat": 43.9487605, "lon": -121.2244484}, {"type": "node", "id": 38584254, "lat": 43.9486142, "lon": -121.2251453}, {"type": "node", "id": 38584256, "lat": 43.9481422, "lon": -121.2264209}, {"type": "node", "id": 38584257, "lat": 43.9477178, "lon": -121.2271177}, {"type": "node", "id": 38584259, "lat": 43.9464089, "lon": -121.2284912}, {"type": "node", "id": 38584261, "lat": 43.9460367, "lon": -121.2291854}, {"type": "node", "id": 38584263, "lat": 43.9454069, "lon": -121.2348358}, {"type": "node", "id": 38584265, "lat": 43.945602, "lon": -121.236609}, {"type": "node", "id": 38584267, "lat": 43.9460748, "lon": -121.2379065}, {"type": "node", "id": 38584270, "lat": 43.9468959, "lon": -121.2400762}, {"type": "node", "id": 38584277, "lat": 43.951531, "lon": -121.2523342}, {"type": "node", "id": 38587488, "lat": 44.0873847, "lon": -121.1858658}, {"type": "node", "id": 38588381, "lat": 44.0593362, "lon": -121.1939847, "tags": {"highway": "turning_circle"}}, {"type": "node", "id": 38588524, "lat": 44.0593889, "lon": -121.1965299}, {"type": "node", "id": 38588526, "lat": 44.0597374, "lon": -121.1971114}, {"type": "node", "id": 38588528, "lat": 44.0600614, "lon": -121.1973506}, {"type": "node", "id": 38588530, "lat": 44.060353, "lon": -121.1974106}, {"type": "node", "id": 38588533, "lat": 44.0626563, "lon": -121.1972413}, {"type": "node", "id": 38588537, "lat": 44.0639548, "lon": -121.1958476}, {"type": "node", "id": 38588539, "lat": 44.0644414, "lon": -121.1952581}, {"type": "node", "id": 38588541, "lat": 44.0648896, "lon": -121.1951189}, {"type": "node", "id": 611151197, "lat": 44.1141871, "lon": -121.2026421}, {"type": "node", "id": 611151199, "lat": 44.1147799, "lon": -121.202819}, {"type": "node", "id": 611151202, "lat": 44.1178457, "lon": -121.2035365}, {"type": "node", "id": 611151205, "lat": 44.1184525, "lon": -121.204077}, {"type": "node", "id": 611151207, "lat": 44.1053467, "lon": -121.1919071}, {"type": "node", "id": 612637130, "lat": 44.0489283, "lon": -121.2035181}, {"type": "node", "id": 612637131, "lat": 44.0479331, "lon": -121.2035017}, {"type": "node", "id": 612637132, "lat": 44.0499078, "lon": -121.2035072}, {"type": "node", "id": 612637140, "lat": 44.0573887, "lon": -121.215976}, {"type": "node", "id": 612637141, "lat": 44.0570205, "lon": -121.2141405}, {"type": "node", "id": 612637152, "lat": 44.06743, "lon": -121.2036962}, {"type": "node", "id": 612637153, "lat": 44.0678901, "lon": -121.2036374}, {"type": "node", "id": 612637154, "lat": 44.0729316, "lon": -121.2035786}, {"type": "node", "id": 612637160, "lat": 44.0783708, "lon": -121.203541}, {"type": "node", "id": 612637161, "lat": 44.0792882, "lon": -121.2035464}, {"type": "node", "id": 612637162, "lat": 44.0873878, "lon": -121.2034014}, {"type": "node", "id": 612637163, "lat": 44.0839188, "lon": -121.2034236}, {"type": "node", "id": 612637164, "lat": 44.0839011, "lon": -121.2018414}, {"type": "node", "id": 612637176, "lat": 44.0517763, "lon": -121.1977998}, {"type": "node", "id": 612637177, "lat": 44.0518805, "lon": -121.1972246}, {"type": "node", "id": 612637178, "lat": 44.0519175, "lon": -121.197435}, {"type": "node", "id": 612637179, "lat": 44.0518772, "lon": -121.1976548}, {"type": "node", "id": 612637180, "lat": 44.0513864, "lon": -121.1955222}, {"type": "node", "id": 612637181, "lat": 44.0511914, "lon": -121.1941706}, {"type": "node", "id": 612637182, "lat": 44.0512486, "lon": -121.1948768}, {"type": "node", "id": 612637183, "lat": 44.0513334, "lon": -121.1980277}, {"type": "node", "id": 612637184, "lat": 44.0512259, "lon": -121.1981414}, {"type": "node", "id": 612637185, "lat": 44.0511807, "lon": -121.1982791}, {"type": "node", "id": 612637186, "lat": 44.0615146, "lon": -121.1959926}, {"type": "node", "id": 612637187, "lat": 44.0618937, "lon": -121.1969262}, {"type": "node", "id": 612637188, "lat": 44.0621345, "lon": -121.1969068}, {"type": "node", "id": 612637189, "lat": 44.0629853, "lon": -121.1971587}, {"type": "node", "id": 612637190, "lat": 44.063421, "lon": -121.1968252}, {"type": "node", "id": 612637191, "lat": 44.0642672, "lon": -121.1970365}, {"type": "node", "id": 612637192, "lat": 44.0657129, "lon": -121.1968259}, {"type": "node", "id": 612637193, "lat": 44.0620674, "lon": -121.1939808}, {"type": "node", "id": 612637194, "lat": 44.0641811, "lon": -121.1955044}, {"type": "node", "id": 612637195, "lat": 44.083841, "lon": -121.2004287}, {"type": "node", "id": 612637196, "lat": 44.0851929, "lon": -121.1960093}, {"type": "node", "id": 612637197, "lat": 44.0847089, "lon": -121.1962463}, {"type": "node", "id": 612637198, "lat": 44.084325, "lon": -121.196646}, {"type": "node", "id": 612637199, "lat": 44.0840146, "lon": -121.1972268}, {"type": "node", "id": 612637200, "lat": 44.0838677, "lon": -121.197752}, {"type": "node", "id": 612637201, "lat": 44.0870621, "lon": -121.1948801}, {"type": "node", "id": 612637203, "lat": 44.0867851, "lon": -121.1952518}, {"type": "node", "id": 612637204, "lat": 44.0865247, "lon": -121.1955028}, {"type": "node", "id": 612637205, "lat": 44.0862243, "lon": -121.1956468}, {"type": "node", "id": 612637207, "lat": 44.0873939, "lon": -121.193218}, {"type": "node", "id": 612637211, "lat": 44.0941832, "lon": -121.1939065}, {"type": "node", "id": 614017085, "lat": 44.0434789, "lon": -121.1692026}, {"type": "node", "id": 614017087, "lat": 44.038582, "lon": -121.1546543}, {"type": "node", "id": 617485353, "lat": 44.0084339, "lon": -121.2559439}, {"type": "node", "id": 617485379, "lat": 44.0244527, "lon": -121.2238733}, {"type": "node", "id": 617485424, "lat": 44.0285839, "lon": -121.223748}, {"type": "node", "id": 617485447, "lat": 44.0161579, "lon": -121.209125}, {"type": "node", "id": 617485448, "lat": 44.0149305, "lon": -121.2086198}, {"type": "node", "id": 617485449, "lat": 44.0149292, "lon": -121.2061982}, {"type": "node", "id": 617485450, "lat": 44.0177371, "lon": -121.2088122}, {"type": "node", "id": 617485451, "lat": 44.0181466, "lon": -121.2086746}, {"type": "node", "id": 617485452, "lat": 44.0216018, "lon": -121.208612}, {"type": "node", "id": 617485453, "lat": 44.0221543, "lon": -121.2042875}, {"type": "node", "id": 617485454, "lat": 44.0224092, "lon": -121.2216495}, {"type": "node", "id": 1780025207, "lat": 44.0080593, "lon": -121.1853409}, {"type": "node", "id": 1780025208, "lat": 44.0081214, "lon": -121.1838526}, {"type": "node", "id": 1797819802, "lat": 43.9855286, "lon": -121.3033664}, {"type": "node", "id": 2578662582, "lat": 44.0077569, "lon": -121.1821884}, {"type": "node", "id": 2578662584, "lat": 44.0078844, "lon": -121.1830236}, {"type": "node", "id": 2578662585, "lat": 44.0079101, "lon": -121.1858152}, {"type": "node", "id": 2578662587, "lat": 44.0080449, "lon": -121.1835417}, {"type": "node", "id": 2578662589, "lat": 44.0081393, "lon": -121.1849358}, {"type": "node", "id": 2578662591, "lat": 44.0081798, "lon": -121.1841893}, {"type": "node", "id": 2578662621, "lat": 44.0142363, "lon": -121.2005425}, {"type": "node", "id": 2578662623, "lat": 44.0142581, "lon": -121.2002556}, {"type": "node", "id": 2578662625, "lat": 44.0143638, "lon": -121.1999408}, {"type": "node", "id": 2578662627, "lat": 44.0144835, "lon": -121.201005}, {"type": "node", "id": 2578662630, "lat": 44.0150749, "lon": -121.1988658}, {"type": "node", "id": 2578662632, "lat": 44.015147, "lon": -121.1985743}, {"type": "node", "id": 2578662635, "lat": 44.0151626, "lon": -121.2089498}, {"type": "node", "id": 2578675671, "lat": 43.9877508, "lon": -121.22101}, {"type": "node", "id": 2578675688, "lat": 43.9879028, "lon": -121.221119}, {"type": "node", "id": 2578675697, "lat": 43.9880242, "lon": -121.2211416}, {"type": "node", "id": 2578675841, "lat": 43.9932807, "lon": -121.2385104}, {"type": "node", "id": 2578675844, "lat": 43.993329, "lon": -121.2387448}, {"type": "node", "id": 2578675848, "lat": 43.9935548, "lon": -121.2390626}, {"type": "node", "id": 2578675866, "lat": 43.996375, "lon": -121.2390964}, {"type": "node", "id": 2578675867, "lat": 43.9967556, "lon": -121.2393395}, {"type": "node", "id": 2578675868, "lat": 43.9968859, "lon": -121.2396676}, {"type": "node", "id": 2773174401, "lat": 43.9383681, "lon": -121.200387}, {"type": "node", "id": 2773175101, "lat": 43.9529486, "lon": -121.2560836}, {"type": "node", "id": 2773211704, "lat": 43.9469415, "lon": -121.2179553}, {"type": "node", "id": 2773240326, "lat": 43.9668684, "lon": -121.1959694}, {"type": "node", "id": 2773240338, "lat": 43.9687703, "lon": -121.1959625}, {"type": "node", "id": 2773240339, "lat": 43.9690889, "lon": -121.1958588}, {"type": "node", "id": 2773240340, "lat": 43.9692831, "lon": -121.1958311}, {"type": "node", "id": 2773240344, "lat": 43.9709011, "lon": -121.1959279}, {"type": "node", "id": 2773240348, "lat": 43.9718022, "lon": -121.195672}, {"type": "node", "id": 2773240350, "lat": 43.972091, "lon": -121.1957896}, {"type": "node", "id": 2773240352, "lat": 43.9736193, "lon": -121.1980654}, {"type": "node", "id": 2773240353, "lat": 43.9738234, "lon": -121.1965228}, {"type": "node", "id": 2773240354, "lat": 43.9762122, "lon": -121.215065}, {"type": "node", "id": 2773240355, "lat": 43.9764516, "lon": -121.2100415}, {"type": "node", "id": 2773240356, "lat": 43.9764586, "lon": -121.2097383}, {"type": "node", "id": 2773240357, "lat": 43.9764727, "lon": -121.2174031}, {"type": "node", "id": 2773240359, "lat": 43.978201, "lon": -121.214615}, {"type": "node", "id": 2806813407, "lat": 43.9415585, "lon": -121.204454}, {"type": "node", "id": 2806813408, "lat": 43.9408046, "lon": -121.2030283}, {"type": "node", "id": 2806813409, "lat": 43.939055, "lon": -121.201646}, {"type": "node", "id": 2806813410, "lat": 43.9385649, "lon": -121.2008824}, {"type": "node", "id": 2814834901, "lat": 44.0142708, "lon": -121.200685}, {"type": "node", "id": 2814834902, "lat": 44.0144025, "lon": -121.2009341}, {"type": "node", "id": 2814834903, "lat": 44.0148525, "lon": -121.2011028}, {"type": "node", "id": 2814834904, "lat": 44.0148984, "lon": -121.2011605}, {"type": "node", "id": 2814834905, "lat": 44.014959, "lon": -121.2013642}, {"type": "node", "id": 2814834906, "lat": 44.0149664, "lon": -121.2015165}, {"type": "node", "id": 2814834907, "lat": 44.0149664, "lon": -121.2018952}, {"type": "node", "id": 2814834909, "lat": 44.0216433, "lon": -121.1962021}, {"type": "node", "id": 2814834910, "lat": 44.0216552, "lon": -121.2001332}, {"type": "node", "id": 2814834911, "lat": 44.0217144, "lon": -121.1957452}, {"type": "node", "id": 2814834912, "lat": 44.0217292, "lon": -121.2010099}, {"type": "node", "id": 2814834917, "lat": 44.0222412, "lon": -121.1932631}, {"type": "node", "id": 2817336075, "lat": 44.1137473, "lon": -121.1817765}, {"type": "node", "id": 3126235855, "lat": 44.0656487, "lon": -121.165018}, {"type": "node", "id": 3180280947, "lat": 43.9761998, "lon": -121.2151635}, {"type": "node", "id": 3180280950, "lat": 43.9762436, "lon": -121.2149161}, {"type": "node", "id": 3180323651, "lat": 43.9687826, "lon": -121.2751411}, {"type": "node", "id": 3189669314, "lat": 43.968289, "lon": -121.2710212}, {"type": "node", "id": 3189669315, "lat": 43.9682254, "lon": -121.2707011}, {"type": "node", "id": 3189669316, "lat": 43.9680375, "lon": -121.2702122}, {"type": "node", "id": 3191181639, "lat": 43.9825665, "lon": -121.3018545}, {"type": "node", "id": 3191181702, "lat": 43.9860877, "lon": -121.3037172}, {"type": "node", "id": 3191181729, "lat": 43.9861756, "lon": -121.3037641}, {"type": "node", "id": 3191221201, "lat": 43.9708499, "lon": -121.2975674}, {"type": "node", "id": 3191221204, "lat": 43.9709604, "lon": -121.2978827}, {"type": "node", "id": 3191221212, "lat": 43.9711807, "lon": -121.2983625}, {"type": "node", "id": 3191221218, "lat": 43.9713067, "lon": -121.2985917}, {"type": "node", "id": 3191221223, "lat": 43.9714535, "lon": -121.2988203}, {"type": "node", "id": 3191221252, "lat": 43.9718165, "lon": -121.2992567}, {"type": "node", "id": 3191221268, "lat": 43.9720762, "lon": -121.2994966}, {"type": "node", "id": 3191221281, "lat": 43.9726255, "lon": -121.2998499}, {"type": "node", "id": 3191221291, "lat": 43.9729667, "lon": -121.2999821}, {"type": "node", "id": 3191221381, "lat": 43.9812746, "lon": -121.3016164}, {"type": "node", "id": 3191221382, "lat": 43.9829893, "lon": -121.3020035}, {"type": "node", "id": 3192279882, "lat": 43.9749515, "lon": -121.3003851}, {"type": "node", "id": 3192279908, "lat": 43.9760115, "lon": -121.3005876}, {"type": "node", "id": 3192279985, "lat": 43.978081, "lon": -121.3009858}, {"type": "node", "id": 3192280115, "lat": 43.9820555, "lon": -121.3017592}, {"type": "node", "id": 3192280167, "lat": 43.9834935, "lon": -121.3022556}, {"type": "node", "id": 3192888805, "lat": 43.9694238, "lon": -121.2810334}, {"type": "node", "id": 3192888806, "lat": 43.9694304, "lon": -121.281609}, {"type": "node", "id": 3192888807, "lat": 43.9694634, "lon": -121.2796184}, {"type": "node", "id": 3192888808, "lat": 43.9694816, "lon": -121.2775773}, {"type": "node", "id": 3192888809, "lat": 43.9694832, "lon": -121.2821732}, {"type": "node", "id": 3192888810, "lat": 43.9695064, "lon": -121.2782332}, {"type": "node", "id": 3192888811, "lat": 43.9695113, "lon": -121.2778892}, {"type": "node", "id": 3192888812, "lat": 43.9696615, "lon": -121.2836937}, {"type": "node", "id": 3192888813, "lat": 43.9698497, "lon": -121.2852898}, {"type": "node", "id": 3192888814, "lat": 43.9703109, "lon": -121.2894358}, {"type": "node", "id": 3192888815, "lat": 43.9703769, "lon": -121.2908645}, {"type": "node", "id": 3192888817, "lat": 43.9704429, "lon": -121.2924722}, {"type": "node", "id": 3192888818, "lat": 43.9705106, "lon": -121.293933}, {"type": "node", "id": 3192888820, "lat": 43.970575, "lon": -121.2953343}, {"type": "node", "id": 3192888821, "lat": 43.9706757, "lon": -121.2967263}, {"type": "node", "id": 3192969590, "lat": 43.9683325, "lon": -121.2728357}, {"type": "node", "id": 3192969591, "lat": 43.9683426, "lon": -121.2732585}, {"type": "node", "id": 3192969592, "lat": 43.9683654, "lon": -121.2735748}, {"type": "node", "id": 3192969593, "lat": 43.9684084, "lon": -121.2738747}, {"type": "node", "id": 3192969595, "lat": 43.9684615, "lon": -121.274116}, {"type": "node", "id": 3192969597, "lat": 43.9685458, "lon": -121.2744311}, {"type": "node", "id": 3192969604, "lat": 43.9691071, "lon": -121.2761286}, {"type": "node", "id": 3192969615, "lat": 43.9701732, "lon": -121.2880884}, {"type": "node", "id": 3199633016, "lat": 43.9543753, "lon": -121.2598251}, {"type": "node", "id": 3199633026, "lat": 43.9548309, "lon": -121.26089}, {"type": "node", "id": 3199633182, "lat": 43.9569489, "lon": -121.2653146}, {"type": "node", "id": 3199633196, "lat": 43.9572723, "lon": -121.265999}, {"type": "node", "id": 3199633218, "lat": 43.9578467, "lon": -121.2669291}, {"type": "node", "id": 3199633277, "lat": 43.9586, "lon": -121.267558}, {"type": "node", "id": 3199633302, "lat": 43.9591896, "lon": -121.2677958}, {"type": "node", "id": 3199633378, "lat": 43.9622633, "lon": -121.2683454}, {"type": "node", "id": 3199633395, "lat": 43.9635509, "lon": -121.2684141}, {"type": "node", "id": 3199633403, "lat": 43.965662, "lon": -121.2685541}, {"type": "node", "id": 3199633406, "lat": 43.9669229, "lon": -121.2689663}, {"type": "node", "id": 3199633408, "lat": 43.9673166, "lon": -121.2692068}, {"type": "node", "id": 3199633409, "lat": 43.967638, "lon": -121.2695344}, {"type": "node", "id": 3199633411, "lat": 43.9679137, "lon": -121.2699599}, {"type": "node", "id": 3199653531, "lat": 43.9694689, "lon": -121.2794401}, {"type": "node", "id": 3199653533, "lat": 43.9695784, "lon": -121.282985}, {"type": "node", "id": 3201107786, "lat": 43.9694667, "lon": -121.2819969}, {"type": "node", "id": 3202623934, "lat": 43.9487022, "lon": -121.2247707}, {"type": "node", "id": 3202623936, "lat": 43.9487708, "lon": -121.2222148}, {"type": "node", "id": 3202623937, "lat": 43.9487868, "lon": -121.2243035}, {"type": "node", "id": 3202623938, "lat": 43.9487982, "lon": -121.224142}, {"type": "node", "id": 3202623939, "lat": 43.9488176, "lon": -121.2226752}, {"type": "node", "id": 3202633174, "lat": 43.9423353, "lon": -121.2067103}, {"type": "node", "id": 3202633180, "lat": 43.9433574, "lon": -121.2081794}, {"type": "node", "id": 3202633181, "lat": 43.9436128, "lon": -121.2084975}, {"type": "node", "id": 3202633182, "lat": 43.9439879, "lon": -121.2091374}, {"type": "node", "id": 3202633183, "lat": 43.944729, "lon": -121.2113897}, {"type": "node", "id": 3202633184, "lat": 43.9455912, "lon": -121.2140462}, {"type": "node", "id": 3202646623, "lat": 43.9453978, "lon": -121.2352813}, {"type": "node", "id": 3202646624, "lat": 43.945423, "lon": -121.2345267}, {"type": "node", "id": 3202646625, "lat": 43.9454263, "lon": -121.2357856}, {"type": "node", "id": 3202646626, "lat": 43.945491, "lon": -121.236179}, {"type": "node", "id": 3202646630, "lat": 43.9457077, "lon": -121.2369447}, {"type": "node", "id": 3215346084, "lat": 43.9375413, "lon": -121.1981296}, {"type": "node", "id": 3215346089, "lat": 43.9377175, "lon": -121.1986641}, {"type": "node", "id": 3215346097, "lat": 43.9387099, "lon": -121.2011767}, {"type": "node", "id": 3215346098, "lat": 43.938928, "lon": -121.2014974}, {"type": "node", "id": 3215346099, "lat": 43.9392484, "lon": -121.2018269}, {"type": "node", "id": 3215346100, "lat": 43.940453, "lon": -121.2025788}, {"type": "node", "id": 3215346101, "lat": 43.9413875, "lon": -121.2040951}, {"type": "node", "id": 3215346102, "lat": 43.9416419, "lon": -121.2046591}, {"type": "node", "id": 3215346103, "lat": 43.9420341, "lon": -121.2058451}, {"type": "node", "id": 3215346104, "lat": 43.9421745, "lon": -121.2062881}, {"type": "node", "id": 3215346105, "lat": 43.9426288, "lon": -121.2072732}, {"type": "node", "id": 3215353908, "lat": 43.9513963, "lon": -121.251976}, {"type": "node", "id": 3216949720, "lat": 43.979335, "lon": -121.2061863}, {"type": "node", "id": 3216949721, "lat": 43.9793479, "lon": -121.2059641}, {"type": "node", "id": 3216949722, "lat": 43.9794937, "lon": -121.2068187}, {"type": "node", "id": 3216949723, "lat": 43.9797329, "lon": -121.210495}, {"type": "node", "id": 3216949724, "lat": 43.9797901, "lon": -121.2097636}, {"type": "node", "id": 3216949725, "lat": 43.9799733, "lon": -121.2074528}, {"type": "node", "id": 3216949726, "lat": 43.9799967, "lon": -121.2094961}, {"type": "node", "id": 3216949727, "lat": 43.9800002, "lon": -121.2221611}, {"type": "node", "id": 3216949728, "lat": 43.9801005, "lon": -121.2218254}, {"type": "node", "id": 3216949729, "lat": 43.9801542, "lon": -121.2077317}, {"type": "node", "id": 3216949730, "lat": 43.9801845, "lon": -121.2117485}, {"type": "node", "id": 3216949731, "lat": 43.980237, "lon": -121.2214914}, {"type": "node", "id": 3216949732, "lat": 43.9802825, "lon": -121.2079977}, {"type": "node", "id": 3216949733, "lat": 43.9803946, "lon": -121.2121507}, {"type": "node", "id": 3216949734, "lat": 43.9804529, "lon": -121.2090517}, {"type": "node", "id": 3216949735, "lat": 43.9804891, "lon": -121.2188951}, {"type": "node", "id": 3216949736, "lat": 43.9805113, "lon": -121.2088766}, {"type": "node", "id": 3216949737, "lat": 43.9805148, "lon": -121.2086269}, {"type": "node", "id": 3216949738, "lat": 43.9805241, "lon": -121.2191027}, {"type": "node", "id": 3216949739, "lat": 43.9805918, "lon": -121.2207503}, {"type": "node", "id": 3216949740, "lat": 43.9806174, "lon": -121.2193443}, {"type": "node", "id": 3216949741, "lat": 43.9807155, "lon": -121.2166183}, {"type": "node", "id": 3216949742, "lat": 43.9807703, "lon": -121.2200854}, {"type": "node", "id": 3216949743, "lat": 43.9807866, "lon": -121.2198259}, {"type": "node", "id": 3216949744, "lat": 43.980964, "lon": -121.2131723}, {"type": "node", "id": 3216949745, "lat": 43.9811052, "lon": -121.2156762}, {"type": "node", "id": 3216949746, "lat": 43.9811787, "lon": -121.2140578}, {"type": "node", "id": 3216949747, "lat": 43.9812336, "lon": -121.2148816}, {"type": "node", "id": 3216949799, "lat": 43.9932241, "lon": -121.1943782}, {"type": "node", "id": 3216949800, "lat": 43.9932504, "lon": -121.1941733}, {"type": "node", "id": 3216949801, "lat": 43.9932667, "lon": -121.194123}, {"type": "node", "id": 3235694893, "lat": 43.9457256, "lon": -121.2307313}, {"type": "node", "id": 3235694894, "lat": 43.9457886, "lon": -121.2300745}, {"type": "node", "id": 3235694896, "lat": 43.9458803, "lon": -121.2296524}, {"type": "node", "id": 3235694905, "lat": 43.9462219, "lon": -121.2287909}, {"type": "node", "id": 3235694915, "lat": 43.9464826, "lon": -121.2167714}, {"type": "node", "id": 3235694920, "lat": 43.9466336, "lon": -121.2282465}, {"type": "node", "id": 3235694922, "lat": 43.946693, "lon": -121.2174007}, {"type": "node", "id": 3235694936, "lat": 43.9471065, "lon": -121.2278269}, {"type": "node", "id": 3235694946, "lat": 43.9474607, "lon": -121.2274648}, {"type": "node", "id": 3235694958, "lat": 43.9479138, "lon": -121.226823}, {"type": "node", "id": 3235694963, "lat": 43.9481134, "lon": -121.2201427}, {"type": "node", "id": 3235694977, "lat": 43.9483705, "lon": -121.2259414}, {"type": "node", "id": 3235694983, "lat": 43.9485287, "lon": -121.225472}, {"type": "node", "id": 3235694984, "lat": 43.9485485, "lon": -121.2212315}, {"type": "node", "id": 3237257625, "lat": 43.9786971, "lon": -121.2142716}, {"type": "node", "id": 3237257626, "lat": 43.9787929, "lon": -121.2173498}, {"type": "node", "id": 3237257627, "lat": 43.979047, "lon": -121.2139735}, {"type": "node", "id": 3237257628, "lat": 43.9793837, "lon": -121.217258}, {"type": "node", "id": 3237257629, "lat": 43.9793869, "lon": -121.2135882}, {"type": "node", "id": 3237257630, "lat": 43.9799315, "lon": -121.213102}, {"type": "node", "id": 3237257631, "lat": 43.9824134, "lon": -121.2119737}, {"type": "node", "id": 3237257632, "lat": 43.9830108, "lon": -121.2119599}, {"type": "node", "id": 3237257633, "lat": 43.9837963, "lon": -121.2121342}, {"type": "node", "id": 3238847072, "lat": 43.9804362, "lon": -121.2063756}, {"type": "node", "id": 3238847073, "lat": 43.9806507, "lon": -121.2064667}, {"type": "node", "id": 3238847075, "lat": 43.9811462, "lon": -121.2161601}, {"type": "node", "id": 3238847078, "lat": 43.9818702, "lon": -121.2067798}, {"type": "node", "id": 3238847079, "lat": 43.9821264, "lon": -121.2069835}, {"type": "node", "id": 3238847080, "lat": 43.9823739, "lon": -121.2165957}, {"type": "node", "id": 3238847081, "lat": 43.9824531, "lon": -121.2073231}, {"type": "node", "id": 3238847082, "lat": 43.9824717, "lon": -121.2166024}, {"type": "node", "id": 3238847084, "lat": 43.9827987, "lon": -121.207507}, {"type": "node", "id": 3238847086, "lat": 43.9830002, "lon": -121.2074441}, {"type": "node", "id": 3238847088, "lat": 43.9831849, "lon": -121.2074126}, {"type": "node", "id": 3238847090, "lat": 43.983589, "lon": -121.2075898}, {"type": "node", "id": 3238847093, "lat": 43.9842397, "lon": -121.2158124}, {"type": "node", "id": 3238847094, "lat": 43.9842408, "lon": -121.2161072}, {"type": "node", "id": 3238847096, "lat": 43.9842677, "lon": -121.2164375}, {"type": "node", "id": 3238847097, "lat": 43.9843402, "lon": -121.2155239}, {"type": "node", "id": 3238847098, "lat": 43.9843402, "lon": -121.2169037}, {"type": "node", "id": 3238847101, "lat": 43.9845155, "lon": -121.214971}, {"type": "node", "id": 3238847103, "lat": 43.9845526, "lon": -121.2138488}, {"type": "node", "id": 3238847104, "lat": 43.984556, "lon": -121.2141909}, {"type": "node", "id": 3238847105, "lat": 43.9845577, "lon": -121.2146899}, {"type": "node", "id": 3238847106, "lat": 43.9845711, "lon": -121.2136755}, {"type": "node", "id": 3238847107, "lat": 43.984595, "lon": -121.2083585}, {"type": "node", "id": 3238847109, "lat": 43.9846229, "lon": -121.2198568}, {"type": "node", "id": 3238847110, "lat": 43.9846364, "lon": -121.219093}, {"type": "node", "id": 3238847111, "lat": 43.9846533, "lon": -121.2194725}, {"type": "node", "id": 3238847112, "lat": 43.9846622, "lon": -121.2132139}, {"type": "node", "id": 3238847113, "lat": 43.9847976, "lon": -121.2083104}, {"type": "node", "id": 3238847114, "lat": 43.9849184, "lon": -121.2125463}, {"type": "node", "id": 3238847116, "lat": 43.9851556, "lon": -121.2181653}, {"type": "node", "id": 3238847117, "lat": 43.9851927, "lon": -121.2182871}, {"type": "node", "id": 3238847118, "lat": 43.9852112, "lon": -121.2079311}, {"type": "node", "id": 3238847119, "lat": 43.9852213, "lon": -121.2184207, "tags": {"highway": "turning_circle"}}, {"type": "node", "id": 3238847120, "lat": 43.9852235, "lon": -121.2121058}, {"type": "node", "id": 3238847121, "lat": 43.9853519, "lon": -121.2079013}, {"type": "node", "id": 3238847122, "lat": 43.9854973, "lon": -121.2079245}, {"type": "node", "id": 3238847123, "lat": 43.985831, "lon": -121.2080686}, {"type": "node", "id": 3238847128, "lat": 43.9858893, "lon": -121.211143}, {"type": "node", "id": 3238847131, "lat": 43.9860027, "lon": -121.2081995}, {"type": "node", "id": 3238847132, "lat": 43.9860562, "lon": -121.210808}, {"type": "node", "id": 3238847133, "lat": 43.9862888, "lon": -121.2102715}, {"type": "node", "id": 3238847134, "lat": 43.9865259, "lon": -121.2089714}, {"type": "node", "id": 3238847135, "lat": 43.9865974, "lon": -121.2091536}, {"type": "node", "id": 3238847136, "lat": 43.9866713, "lon": -121.2093855}, {"type": "node", "id": 3238847137, "lat": 43.9867464, "lon": -121.2095578}, {"type": "node", "id": 3238847138, "lat": 43.9869788, "lon": -121.2097285}, {"type": "node", "id": 3251296431, "lat": 44.0390869, "lon": -121.1554023}, {"type": "node", "id": 3251296432, "lat": 44.0388694, "lon": -121.1550576}, {"type": "node", "id": 3251296433, "lat": 44.039354, "lon": -121.1558888}, {"type": "node", "id": 3251296447, "lat": 44.0454546, "lon": -121.1775737}, {"type": "node", "id": 3251296448, "lat": 44.0513102, "lon": -121.1952346}, {"type": "node", "id": 3251308973, "lat": 44.0541041, "lon": -121.2063169}, {"type": "node", "id": 3251308979, "lat": 44.0560785, "lon": -121.237637}, {"type": "node", "id": 3683087957, "lat": 44.0738462, "lon": -121.1508704}, {"type": "node", "id": 3683087958, "lat": 44.0738623, "lon": -121.1506335}, {"type": "node", "id": 3683087959, "lat": 44.0739377, "lon": -121.1427396}, {"type": "node", "id": 3683087960, "lat": 44.0739121, "lon": -121.1414121}, {"type": "node", "id": 3683087961, "lat": 44.0728555, "lon": -121.1305546}, {"type": "node", "id": 3683087962, "lat": 44.0714669, "lon": -121.1224832}, {"type": "node", "id": 3683087963, "lat": 44.0717525, "lon": -121.120672}, {"type": "node", "id": 3683087964, "lat": 44.0718425, "lon": -121.1190651}, {"type": "node", "id": 3683087965, "lat": 44.0721315, "lon": -121.1178649}, {"type": "node", "id": 3683087966, "lat": 44.0729597, "lon": -121.1149134}, {"type": "node", "id": 3683087967, "lat": 44.0730741, "lon": -121.1127937}, {"type": "node", "id": 3683087968, "lat": 44.0729311, "lon": -121.1021263}, {"type": "node", "id": 3683087969, "lat": 44.0729986, "lon": -121.0970685}, {"type": "node", "id": 3683087970, "lat": 44.0730741, "lon": -121.0965902}, {"type": "node", "id": 3683087971, "lat": 44.0749124, "lon": -121.0899805}, {"type": "node", "id": 3683111531, "lat": 44.0661014, "lon": -121.1618262}, {"type": "node", "id": 3683118925, "lat": 44.0947938, "lon": -121.1827652}, {"type": "node", "id": 3683118926, "lat": 44.0949348, "lon": -121.1830676}, {"type": "node", "id": 3683118927, "lat": 44.0958944, "lon": -121.1842427}, {"type": "node", "id": 3683118928, "lat": 44.1023461, "lon": -121.1916143}, {"type": "node", "id": 3683118929, "lat": 44.1035775, "lon": -121.1930217}, {"type": "node", "id": 3683118930, "lat": 44.1048334, "lon": -121.1932677}, {"type": "node", "id": 3683118931, "lat": 44.0872658, "lon": -121.1943418}, {"type": "node", "id": 3683123710, "lat": 43.9972182, "lon": -121.2439378}, {"type": "node", "id": 3683123711, "lat": 43.9969882, "lon": -121.2433019}, {"type": "node", "id": 3683123712, "lat": 44.0077765, "lon": -121.2400859}, {"type": "node", "id": 3683292973, "lat": 44.0662323, "lon": -121.1678791}, {"type": "node", "id": 3683292974, "lat": 44.066296, "lon": -121.1688314}, {"type": "node", "id": 3683292975, "lat": 44.0662778, "lon": -121.1692739}, {"type": "node", "id": 3683292976, "lat": 44.0662267, "lon": -121.1697623}, {"type": "node", "id": 3683292977, "lat": 44.0658942, "lon": -121.1724727}, {"type": "node", "id": 3683292978, "lat": 44.0646619, "lon": -121.195134}, {"type": "node", "id": 3683292979, "lat": 44.0652871, "lon": -121.1951038}, {"type": "node", "id": 3789303921, "lat": 44.0655181, "lon": -121.164182}, {"type": "node", "id": 3789303924, "lat": 44.0655619, "lon": -121.1629124}, {"type": "node", "id": 3789303925, "lat": 44.0655681, "lon": -121.1645708}, {"type": "node", "id": 3789303926, "lat": 44.0656036, "lon": -121.162709}, {"type": "node", "id": 3789303927, "lat": 44.0656402, "lon": -121.1935184}, {"type": "node", "id": 3789303929, "lat": 44.065717, "lon": -121.1896766}, {"type": "node", "id": 3789303930, "lat": 44.065718, "lon": -121.1972447}, {"type": "node", "id": 3789303932, "lat": 44.0657259, "lon": -121.1892339}, {"type": "node", "id": 3789303933, "lat": 44.0657509, "lon": -121.1881403}, {"type": "node", "id": 3789303934, "lat": 44.0657631, "lon": -121.1876165}, {"type": "node", "id": 3789303936, "lat": 44.0657713, "lon": -121.1871604}, {"type": "node", "id": 3789303937, "lat": 44.0657725, "lon": -121.1857429}, {"type": "node", "id": 3789303938, "lat": 44.0657749, "lon": -121.1864505}, {"type": "node", "id": 3789303939, "lat": 44.0657963, "lon": -121.1621972}, {"type": "node", "id": 3789303940, "lat": 44.0657963, "lon": -121.1810824}, {"type": "node", "id": 3789303941, "lat": 44.0658077, "lon": -121.17896}, {"type": "node", "id": 3789303943, "lat": 44.0658156, "lon": -121.1766985}, {"type": "node", "id": 3789303944, "lat": 44.065827, "lon": -121.1738191}, {"type": "node", "id": 3789303946, "lat": 44.0658656, "lon": -121.1728155}, {"type": "node", "id": 3789303948, "lat": 44.0658959, "lon": -121.1620453}, {"type": "node", "id": 3789303953, "lat": 44.0659778, "lon": -121.1619469}, {"type": "node", "id": 3789304760, "lat": 44.066187, "lon": -121.1676067}, {"type": "node", "id": 3789304773, "lat": 44.0662699, "lon": -121.1682293}, {"type": "node", "id": 3789304854, "lat": 44.0667069, "lon": -121.161377}, {"type": "node", "id": 3789304905, "lat": 44.0673219, "lon": -121.1608898}, {"type": "node", "id": 3789304933, "lat": 44.0678711, "lon": -121.1604629}, {"type": "node", "id": 3789304950, "lat": 44.0682742, "lon": -121.1600986}, {"type": "node", "id": 3789304964, "lat": 44.0686484, "lon": -121.159665}, {"type": "node", "id": 3789304984, "lat": 44.0691253, "lon": -121.1589744}, {"type": "node", "id": 3789305022, "lat": 44.0701594, "lon": -121.1574301}, {"type": "node", "id": 3789305048, "lat": 44.0711807, "lon": -121.1247281}, {"type": "node", "id": 3789305049, "lat": 44.0712128, "lon": -121.1238341}, {"type": "node", "id": 3789305054, "lat": 44.0713543, "lon": -121.1229852}, {"type": "node", "id": 3789305056, "lat": 44.0714103, "lon": -121.1555438}, {"type": "node", "id": 3789305060, "lat": 44.0715276, "lon": -121.1267373}, {"type": "node", "id": 3789305063, "lat": 44.071616, "lon": -121.1218342}, {"type": "node", "id": 3789305066, "lat": 44.0716947, "lon": -121.121452}, {"type": "node", "id": 3789305070, "lat": 44.0717652, "lon": -121.1550051}, {"type": "node", "id": 3789305071, "lat": 44.071775, "lon": -121.1076891}, {"type": "node", "id": 3789305072, "lat": 44.0717863, "lon": -121.1070186}, {"type": "node", "id": 3789305073, "lat": 44.0717991, "lon": -121.1193757}, {"type": "node", "id": 3789305076, "lat": 44.0718698, "lon": -121.1083216}, {"type": "node", "id": 3789305079, "lat": 44.071926, "lon": -121.1062028}, {"type": "node", "id": 3789305080, "lat": 44.07195, "lon": -121.1185488}, {"type": "node", "id": 3789305083, "lat": 44.072003, "lon": -121.1088691}, {"type": "node", "id": 3789305087, "lat": 44.0720962, "lon": -121.1054876}, {"type": "node", "id": 3789305090, "lat": 44.0721731, "lon": -121.1286191}, {"type": "node", "id": 3789305092, "lat": 44.0721909, "lon": -121.1095083}, {"type": "node", "id": 3789305103, "lat": 44.0726403, "lon": -121.1534339}, {"type": "node", "id": 3789305107, "lat": 44.0728187, "lon": -121.1116204}, {"type": "node", "id": 3789305108, "lat": 44.0728653, "lon": -121.1024414}, {"type": "node", "id": 3789305110, "lat": 44.0729263, "lon": -121.1120361}, {"type": "node", "id": 3789305111, "lat": 44.0729617, "lon": -121.0974306}, {"type": "node", "id": 3789305112, "lat": 44.0729711, "lon": -121.1309569}, {"type": "node", "id": 3789305113, "lat": 44.0729809, "lon": -121.1018312}, {"type": "node", "id": 3789305114, "lat": 44.0729857, "lon": -121.0999606}, {"type": "node", "id": 3789305116, "lat": 44.0730227, "lon": -121.1010423}, {"type": "node", "id": 3789305118, "lat": 44.0730626, "lon": -121.1313391}, {"type": "node", "id": 3789305119, "lat": 44.0730773, "lon": -121.1135022}, {"type": "node", "id": 3789305121, "lat": 44.0730949, "lon": -121.1130776}, {"type": "node", "id": 3789305125, "lat": 44.0732345, "lon": -121.1326108}, {"type": "node", "id": 3789305126, "lat": 44.0732619, "lon": -121.0958147}, {"type": "node", "id": 3789305135, "lat": 44.073445, "lon": -121.0951867}, {"type": "node", "id": 3789305136, "lat": 44.0734721, "lon": -121.1519522}, {"type": "node", "id": 3789305139, "lat": 44.0736616, "lon": -121.1515745}, {"type": "node", "id": 3789305142, "lat": 44.0737774, "lon": -121.0941072}, {"type": "node", "id": 3789305143, "lat": 44.0737916, "lon": -121.1456943}, {"type": "node", "id": 3789305145, "lat": 44.0738061, "lon": -121.1511208}, {"type": "node", "id": 3789305147, "lat": 44.0738221, "lon": -121.1385625}, {"type": "node", "id": 3789305148, "lat": 44.0738286, "lon": -121.1482309}, {"type": "node", "id": 3789305149, "lat": 44.0738526, "lon": -121.1495317}, {"type": "node", "id": 3789305150, "lat": 44.0738591, "lon": -121.1502245}, {"type": "node", "id": 3789305152, "lat": 44.0738703, "lon": -121.1399728}, {"type": "node", "id": 3789305153, "lat": 44.0739185, "lon": -121.1432514}, {"type": "node", "id": 3789305155, "lat": 44.0739394, "lon": -121.1423306}, {"type": "node", "id": 3789305168, "lat": 44.0747616, "lon": -121.0908464}, {"type": "node", "id": 3789305171, "lat": 44.0748949, "lon": -121.0902631}, {"type": "node", "id": 3789305172, "lat": 44.0749029, "lon": -121.0897311}, {"type": "node", "id": 3789368177, "lat": 44.0873905, "lon": -121.1773551}, {"type": "node", "id": 3789379125, "lat": 44.0657834, "lon": -121.1834733}, {"type": "node", "id": 3789393535, "lat": 44.0873915, "lon": -121.1758723}, {"type": "node", "id": 4132081090, "lat": 44.0548745, "lon": -121.2512666}, {"type": "node", "id": 4305127134, "lat": 43.9374033, "lon": -121.1978119}, {"type": "node", "id": 4385977394, "lat": 43.9932161, "lon": -121.2067495}, {"type": "node", "id": 4385993923, "lat": 44.0963717, "lon": -121.193956}, {"type": "node", "id": 4386018574, "lat": 44.1024256, "lon": -121.2028943}, {"type": "node", "id": 4386018575, "lat": 44.1014772, "lon": -121.2032955}, {"type": "node", "id": 4386018576, "lat": 44.1046417, "lon": -121.1990518}, {"type": "node", "id": 4386018577, "lat": 44.10427, "lon": -121.2004227}, {"type": "node", "id": 4386018578, "lat": 44.1051478, "lon": -121.1922577}, {"type": "node", "id": 4386020018, "lat": 44.094653, "lon": -121.1806733}, {"type": "node", "id": 4603479377, "lat": 43.9932337, "lon": -121.2024769}, {"type": "node", "id": 4693055820, "lat": 44.0552627, "lon": -121.2441495}, {"type": "node", "id": 4693056892, "lat": 44.089279, "lon": -121.2034015}, {"type": "node", "id": 4693135825, "lat": 44.0505068, "lon": -121.1933867}, {"type": "node", "id": 4693135830, "lat": 44.0502805, "lon": -121.1937596}, {"type": "node", "id": 4693137406, "lat": 44.0404625, "lon": -121.159131}, {"type": "node", "id": 5061165828, "lat": 44.065564, "lon": -121.2027756}, {"type": "node", "id": 5518006062, "lat": 44.1104783, "lon": -121.1985664}, {"type": "node", "id": 5518047559, "lat": 44.1124339, "lon": -121.1833522}, {"type": "node", "id": 5519048649, "lat": 44.1193302, "lon": -121.2050349}, {"type": "node", "id": 5618067131, "lat": 44.0512279, "lon": -121.2323551}, {"type": "node", "id": 5618067139, "lat": 44.051209, "lon": -121.2293725}, {"type": "node", "id": 5618281349, "lat": 44.0085152, "lon": -121.2561799}, {"type": "node", "id": 7643971159, "lat": 44.061179, "lon": -121.1969514}, {"type": "node", "id": 7643971160, "lat": 44.0612431, "lon": -121.1965232}, {"type": "node", "id": 7643971161, "lat": 44.0620162, "lon": -121.1968974}, {"type": "node", "id": 7643971162, "lat": 44.0605035, "lon": -121.1973875}, {"type": "node", "id": 7643971163, "lat": 44.060184, "lon": -121.1974011}, {"type": "node", "id": 7643971164, "lat": 44.0599058, "lon": -121.1972587}, {"type": "node", "id": 7643971165, "lat": 44.0595421, "lon": -121.1968353}, {"type": "node", "id": 7643975464, "lat": 44.0511527, "lon": -121.206952}, {"type": "node", "id": 7643978628, "lat": 44.0615948, "lon": -121.1945114}, {"type": "node", "id": 7643978629, "lat": 44.0619897, "lon": -121.1941041}, {"type": "node", "id": 7643978630, "lat": 44.0621167, "lon": -121.1938319}, {"type": "node", "id": 7643978631, "lat": 44.0615711, "lon": -121.1949714}, {"type": "node", "id": 7643978632, "lat": 44.06163, "lon": -121.1955058}, {"type": "node", "id": 7643978633, "lat": 44.0623398, "lon": -121.1970588}, {"type": "node", "id": 7643978634, "lat": 44.0625417, "lon": -121.1971954}, {"type": "node", "id": 7643978635, "lat": 44.0627721, "lon": -121.1972393}, {"type": "node", "id": 7643978636, "lat": 44.0628797, "lon": -121.1972078}, {"type": "node", "id": 7643978637, "lat": 44.0632242, "lon": -121.1969861}, {"type": "node", "id": 7643978638, "lat": 44.0635665, "lon": -121.1966501}, {"type": "node", "id": 7643978689, "lat": 44.0617365, "lon": -121.1934151}, {"type": "node", "id": 7982212213, "lat": 43.9384682, "lon": -121.2006428}, {"type": "node", "id": 7982212214, "lat": 43.9386584, "lon": -121.2010798}, {"type": "node", "id": 7982212215, "lat": 43.9386117, "lon": -121.2009846}, {"type": "node", "id": 7982212216, "lat": 43.9385174, "lon": -121.2007673}, {"type": "node", "id": 7982212217, "lat": 43.9388762, "lon": -121.2014291}, {"type": "node", "id": 7982212218, "lat": 43.9388242, "lon": -121.2013576}, {"type": "node", "id": 7982212219, "lat": 43.9389928, "lon": -121.2015746}, {"type": "node", "id": 7982212220, "lat": 43.9393744, "lon": -121.2019269}, {"type": "node", "id": 7982212221, "lat": 43.9393081, "lon": -121.201877}, {"type": "node", "id": 7982212222, "lat": 43.9391759, "lon": -121.2017655}, {"type": "node", "id": 7982212223, "lat": 43.9391181, "lon": -121.2017126}, {"type": "node", "id": 7982212224, "lat": 43.9394625, "lon": -121.201985}, {"type": "node", "id": 7982212225, "lat": 43.9397851, "lon": -121.20217}, {"type": "node", "id": 7982212226, "lat": 43.9396717, "lon": -121.2021065}, {"type": "node", "id": 7982212227, "lat": 43.9400902, "lon": -121.2023413}, {"type": "node", "id": 7982212228, "lat": 43.9399416, "lon": -121.2022572}, {"type": "node", "id": 7982212233, "lat": 43.9417198, "lon": -121.2048772}, {"type": "node", "id": 7982212234, "lat": 43.9417601, "lon": -121.204999}, {"type": "node", "id": 7982212235, "lat": 43.9416799, "lon": -121.2047628}, {"type": "node", "id": 7982212236, "lat": 43.9416015, "lon": -121.2045574}, {"type": "node", "id": 7982212237, "lat": 43.9415112, "lon": -121.2043489}, {"type": "node", "id": 7982212238, "lat": 43.9414506, "lon": -121.204222}, {"type": "node", "id": 7982212239, "lat": 43.9413395, "lon": -121.2040014}, {"type": "node", "id": 7982212240, "lat": 43.9412652, "lon": -121.2038705}, {"type": "node", "id": 7982212241, "lat": 43.9409768, "lon": -121.2033499}, {"type": "node", "id": 7982212242, "lat": 43.9411285, "lon": -121.203635}, {"type": "node", "id": 7982212243, "lat": 43.9410558, "lon": -121.2035035}, {"type": "node", "id": 7982212244, "lat": 43.9405626, "lon": -121.2026871}, {"type": "node", "id": 7982212245, "lat": 43.9405098, "lon": -121.2026309}, {"type": "node", "id": 7982212246, "lat": 43.9403928, "lon": -121.2025319}, {"type": "node", "id": 7982212247, "lat": 43.9403308, "lon": -121.2024892}, {"type": "node", "id": 7982212248, "lat": 43.9401818, "lon": -121.2023959}, {"type": "node", "id": 7982212249, "lat": 43.9409116, "lon": -121.2032287}, {"type": "node", "id": 7982212250, "lat": 43.9408555, "lon": -121.2031219}, {"type": "node", "id": 7982212251, "lat": 43.9407089, "lon": -121.2028763}, {"type": "node", "id": 7982212252, "lat": 43.9407556, "lon": -121.2029477}, {"type": "node", "id": 7982212253, "lat": 43.9406636, "lon": -121.202813}, {"type": "node", "id": 8066067510, "lat": 44.0927238, "lon": -121.1938981}, {"type": "node", "id": 8066067511, "lat": 44.0927197, "lon": -121.1935437}, {"type": "node", "id": 8066067512, "lat": 44.092752, "lon": -121.1933751}, {"type": "node", "id": 8066067513, "lat": 44.092832, "lon": -121.1931744}, {"type": "node", "id": 8066067514, "lat": 44.0929318, "lon": -121.1929072}, {"type": "node", "id": 8066067515, "lat": 44.092992, "lon": -121.192698}, {"type": "node", "id": 8066067516, "lat": 44.0930747, "lon": -121.1924062}, {"type": "node", "id": 8066067517, "lat": 44.0931368, "lon": -121.1920812}, {"type": "node", "id": 8066067518, "lat": 44.0931931, "lon": -121.1918886}, {"type": "node", "id": 8066067519, "lat": 44.0932956, "lon": -121.1917655}, {"type": "node", "id": 8066067520, "lat": 44.0934277, "lon": -121.1916867}, {"type": "node", "id": 8066067521, "lat": 44.0935842, "lon": -121.1916696}, {"type": "node", "id": 8066067522, "lat": 44.0936534, "lon": -121.1916775}, {"type": "node", "id": 8066067523, "lat": 44.0938809, "lon": -121.1916828}, {"type": "node", "id": 8066067524, "lat": 44.0940741, "lon": -121.1916619}, {"type": "node", "id": 8066067529, "lat": 44.0946322, "lon": -121.1914481}, {"type": "node", "id": 8719677555, "lat": 43.9932604, "lon": -121.2382772}, {"type": "node", "id": 8719677556, "lat": 43.993424, "lon": -121.2389134}, {"type": "node", "id": 8719677557, "lat": 43.9939269, "lon": -121.2391655}, {"type": "node", "id": 8719677560, "lat": 43.9876756, "lon": -121.2197212}, {"type": "node", "id": 8719894038, "lat": 44.0097554, "lon": -121.2588785}, {"type": "node", "id": 8719894041, "lat": 44.0096559, "lon": -121.2585504}, {"type": "node", "id": 8719894099, "lat": 44.0083715, "lon": -121.2556599}, {"type": "node", "id": 8719894719, "lat": 43.9974706, "lon": -121.2440544}, {"type": "node", "id": 8719894720, "lat": 43.9976916, "lon": -121.2440565}, {"type": "node", "id": 8719894721, "lat": 44.0014748, "lon": -121.2438956}, {"type": "node", "id": 8719894722, "lat": 44.0010348, "lon": -121.2439543}, {"type": "node", "id": 8719894723, "lat": 44.0012816, "lon": -121.2439115}, {"type": "node", "id": 8719894724, "lat": 43.997125, "lon": -121.243825}, {"type": "node", "id": 8719894725, "lat": 43.9970596, "lon": -121.2436997}, {"type": "node", "id": 8719894726, "lat": 43.9970192, "lon": -121.2435525}, {"type": "node", "id": 8719894727, "lat": 43.9969617, "lon": -121.2426593}, {"type": "node", "id": 8719894728, "lat": 43.9968365, "lon": -121.2394982}, {"type": "node", "id": 8719894729, "lat": 43.9966427, "lon": -121.2392073}, {"type": "node", "id": 8719894730, "lat": 43.9965098, "lon": -121.2391266}, {"type": "node", "id": 8720086903, "lat": 44.0075553, "lon": -121.2437388}, {"type": "node", "id": 8720087798, "lat": 44.0287933, "lon": -121.2237641}, {"type": "way", "id": 5346006, "nodes": [38178162, 612637191, 38178164], "tags": {"highway": "residential", "name": "Carolyn Court", "tiger:cfcc": "A41", "tiger:county": "Deschutes, OR", "tiger:name_base": "Carolyn", "tiger:name_type": "Ct"}}, {"type": "way", "id": 5348965, "nodes": [38209256, 38209259, 38209261, 38209265, 38209269, 8719677560, 38209220, 38209274, 38209277, 2578675671, 2578675688, 2578675697], "tags": {"highway": "residential", "tiger:cfcc": "A41", "tiger:county": "Deschutes, OR", "tiger:reviewed": "no"}}, {"type": "way", "id": 5357733, "nodes": [38312889, 8066067510, 612637211, 38312890, 4385993923], "tags": {"highway": "unclassified", "maxspeed": "25 mph", "name": "Gibson Air Road", "tiger:cfcc": "A41", "tiger:county": "Deschutes, OR"}}, {"type": "way", "id": 5369407, "nodes": [38466165, 38466167, 7643978630, 612637193, 7643978629, 38466169, 7643978628, 38466171, 7643978631, 38466173, 7643978632, 38466175, 612637186, 38466176, 7643971160, 38466179, 7643971159, 38466181], "tags": {"highway": "residential", "name": "Martee Lane", "tiger:cfcc": "A41", "tiger:county": "Deschutes, OR", "tiger:name_base": "Martee", "tiger:name_type": "Ln"}}, {"type": "way", "id": 5369977, "nodes": [38473195, 38473196, 38473198, 2773240359, 3237257625, 3237257627, 3237257629, 38473200, 3237257630, 38473202, 38473204, 3237257631, 3237257632, 38473206, 3237257633, 38473208, 38473209], "tags": {"highway": "residential", "name": "Edmonton Drive", "tiger:cfcc": "A41", "tiger:county": "Deschutes, OR", "tiger:name_base": "Edmonton", "tiger:name_type": "Dr"}}, {"type": "way", "id": 5370341, "nodes": [38478064, 3238847109, 3238847111, 3238847110, 38478073, 3238847098, 3238847096, 3238847094, 38478075, 3238847093, 3238847097, 3238847101, 38478077, 3238847105, 3238847104, 3238847103, 3238847106, 38478079, 3238847112, 38473209, 3238847114, 3238847120, 38478084, 3238847128, 3238847132, 38478086, 3238847133, 38291959], "tags": {"highway": "residential", "name": "Quebec Drive", "tiger:cfcc": "A41", "tiger:county": "Deschutes, OR", "tiger:name_base": "Quebec", "tiger:name_type": "Dr"}}, {"type": "way", "id": 5370638, "nodes": [38482972, 38543756], "tags": {"highway": "residential", "name": "Latigo Court", "tiger:cfcc": "A41", "tiger:county": "Deschutes, OR", "tiger:name_base": "Latigo", "tiger:name_type": "Ct", "tiger:reviewed": "no"}}, {"type": "way", "id": 5371869, "nodes": [38495083, 4693135825, 38489405, 38502803, 7643978689, 38466165, 38502813], "tags": {"highway": "residential", "name": "Byram Road", "tiger:cfcc": "A41", "tiger:county": "Deschutes, OR", "tiger:name_base": "Byram", "tiger:name_type": "Rd"}}, {"type": "way", "id": 5372045, "nodes": [38518197, 8720086903, 8719894721, 8719894723, 8719894722, 38505642, 8719894720, 8719894719, 38298782, 3683123710, 8719894724, 8719894725, 8719894726, 3683123711, 8719894727, 38479644, 38505645, 2578675868, 8719894728, 2578675867, 8719894729, 8719894730, 2578675866, 8719677557, 38505650, 2578675848, 8719677556, 2578675844, 2578675841, 8719677555, 38505652, 38222323, 38222332, 38505661, 38209249, 38505667, 4385977394, 4603479377, 3216949799, 3216949800, 3216949801, 38487096], "tags": {"highway": "tertiary", "lanes": "2", "name": "Arnold Market Road", "name_1": "Arnold Mkt Loop Road", "tiger:cfcc": "A41", "tiger:county": "Deschutes, OR", "tiger:name_base": "Arnold Market;Arnold Market Loop", "tiger:name_base_1": "Arnold Mkt Loop", "tiger:name_type": "Rd", "tiger:name_type_1": "Rd", "tiger:reviewed": "no"}}, {"type": "way", "id": 5372179, "nodes": [38507650, 38507651, 38507654, 38507656, 4386020018, 38290589, 38507660, 3683118925, 3683118926, 38507663, 3683118927, 38507667, 38507669, 38507670, 3683118928, 38507672, 3683118929, 38308105, 38507674, 38507675, 38507676, 38507677, 38507678, 38507679, 38507680, 38507683, 38507685, 38507687, 38507689, 5518006062, 38507691, 38507692, 38507693, 38507695, 38507697, 38507699, 611151197, 611151199, 38507701, 38507703, 611151202, 611151205, 38262933, 5519048649], "tags": {"highway": "unclassified", "name": "McGrath Road", "name_1": "Stenkamp Road", "tiger:cfcc": "A41", "tiger:county": "Deschutes, OR", "tiger:name_base": "McGrath", "tiger:name_base_1": "Stenkamp", "tiger:name_type": "Rd", "tiger:name_type_1": "Rd", "tiger:reviewed": "no"}}, {"type": "way", "id": 5373045, "nodes": [38517749, 8066067529, 38290590], "tags": {"highway": "residential", "name": "Peacock Lane", "tiger:cfcc": "A41", "tiger:county": "Deschutes, OR", "tiger:name_base": "Peacock", "tiger:name_type": "Ln", "tiger:reviewed": "no"}}, {"type": "way", "id": 5373108, "nodes": [38464467, 38518723, 612637131, 612637130, 38518727, 612637132, 38489413], "tags": {"highway": "residential", "name": "Teal Road", "tiger:cfcc": "A41", "tiger:county": "Deschutes, OR", "tiger:name_base": "Teal", "tiger:name_type": "Rd"}}, {"type": "way", "id": 5373328, "nodes": [38521841, 38521842], "tags": {"highway": "residential", "name": "Sage Court", "tiger:cfcc": "A41", "tiger:county": "Deschutes, OR", "tiger:name_base": "Sage", "tiger:name_type": "Ct", "tiger:reviewed": "no"}}, {"type": "way", "id": 5373374, "nodes": [38522502, 3238847075, 38522503, 38522504, 3238847080, 3238847082, 38522505, 38478075], "tags": {"highway": "residential", "name": "Sweetgrass Lane", "tiger:cfcc": "A41", "tiger:county": "Deschutes, OR", "tiger:name_base": "Sweetgrass", "tiger:name_type": "Ln"}}, {"type": "way", "id": 5373676, "nodes": [38526657, 38526659, 38526662, 38526664, 3238847072, 3238847073, 38526666, 38526668, 3238847078, 3238847079, 3238847081, 38526672, 3238847084, 3238847086, 3238847088, 38526675, 3238847090, 38209435, 38526681, 3238847107, 38526683, 3238847113, 38526685, 3238847118, 3238847121, 3238847122, 38526687, 3238847123, 3238847131, 38526689, 3238847134, 3238847135, 3238847136, 3238847137, 38291959, 3238847138], "tags": {"highway": "residential", "name": "Stirling Drive", "tiger:cfcc": "A41", "tiger:county": "Deschutes, OR", "tiger:name_base": "Stirling", "tiger:name_type": "Dr"}}, {"type": "way", "id": 5374261, "nodes": [38526662, 3216949721, 3216949720, 38534324, 38534325, 3216949722, 3216949725, 3216949729, 3216949732, 38534328, 3216949737, 3216949736, 3216949734, 38534332, 3216949726, 3216949724, 38534334, 38534337, 3216949723, 38534341, 3216949730, 3216949733, 38473202, 3216949744, 38534345, 3216949746, 38534348, 3216949747, 38534352, 3216949745, 38522502, 38534357, 3216949741, 38534361, 38534364, 3216949735, 3216949738, 3216949740, 38534365, 3216949743, 3216949742, 38478067, 3216949739, 3216949731, 3216949728, 3216949727, 38534369, 38534372], "tags": {"highway": "residential", "name": "Sweetgrass Drive", "name_1": "Sweet Grass Drive", "tiger:cfcc": "A41", "tiger:county": "Deschutes, OR", "tiger:name_base": "Sweetgrass", "tiger:name_base_1": "Sweet Grass", "tiger:name_type": "Dr", "tiger:name_type_1": "Dr"}}, {"type": "way", "id": 5374942, "nodes": [38478073, 38543338, 3238847116, 3238847117, 3238847119], "tags": {"highway": "residential", "name": "Vancouver Lane", "tiger:cfcc": "A41", "tiger:county": "Deschutes, OR", "tiger:name_base": "Vancouver", "tiger:name_type": "Ln"}}, {"type": "way", "id": 5375113, "nodes": [38545423, 2773240326, 38545424, 2773240338, 2773240339, 2773240340, 38545427, 2773240344, 38545430, 38545432, 2773240348, 2773240350, 38545434, 38545437, 38545439, 2773240353, 38545441, 2773240352, 38545443, 38545445, 38545447, 38545449, 38471925, 38227571, 38545452, 38545453, 38227565, 38545454, 38545455, 38526657, 38545456, 38239211, 38545458, 38545460, 38545461, 38545462, 38545463, 2773240356, 2773240355, 38531980, 38545464, 38545465, 38545466, 38473195, 3180280950, 2773240354, 3180280947, 38239257, 38545467, 38545468, 38545469, 38545470, 2773240357, 38239270, 3237257626, 3237257628, 38545471, 38534361], "tags": {"highway": "residential", "name": "Calgary Drive", "tiger:cfcc": "A41", "tiger:county": "Deschutes, OR", "tiger:name_base": "Calgary", "tiger:name_type": "Dr"}}, {"type": "way", "id": 5375142, "nodes": [38239533, 38545956, 38545957, 38239582, 38398650, 38545958, 38545959, 38481572, 2817336075, 5518047559, 38545964, 611151207, 4386018578, 38308107, 3683118930, 38507676, 38545965, 38545966, 4386018576, 38545967, 4386018577, 38545968, 38545969, 38545970, 4386018574, 38545971, 4386018575, 38545973, 38545975, 38278043, 4693056892, 612637162, 612637163, 38494173, 612637161, 612637160, 612637154, 38545984, 612637153, 612637152], "tags": {"highway": "secondary", "name": "Powell Butte Highway", "tiger:cfcc": "A41", "tiger:county": "Deschutes, OR", "tiger:name_base": "Powell Butte", "tiger:name_base_1": "Powell Butte", "tiger:name_type": "Rd", "tiger:name_type_1": "Hwy", "tiger:reviewed": "no"}}, {"type": "way", "id": 5375507, "nodes": [38485180, 38550194], "tags": {"highway": "residential", "name": "Buckskin Court", "tiger:cfcc": "A41", "tiger:county": "Deschutes, OR", "tiger:name_base": "Buckskin", "tiger:name_type": "Ct", "tiger:reviewed": "no"}}, {"type": "way", "id": 5378255, "nodes": [38533401, 38582037, 2578662632, 2578662630, 38582041, 38582043, 2578662625, 2578662623, 2578662621, 2814834901, 38582046, 2814834902, 2578662627, 38316471, 2814834903, 2814834904, 2814834905, 2814834906, 2814834907, 617485449, 617485448, 38582059], "tags": {"highway": "residential", "name": "McArdle Road", "tiger:cfcc": "A41", "tiger:county": "Deschutes, OR", "tiger:name_base": "McArdle", "tiger:name_type": "Rd", "tiger:reviewed": "no", "tracktype": "grade3"}}, {"type": "way", "id": 5378369, "nodes": [38553309, 617485452, 38583629], "tags": {"highway": "unclassified", "name": "Sum View Drive", "surface": "unpaved", "tiger:cfcc": "A41", "tiger:county": "Deschutes, OR", "tiger:name_base": "Sumview", "tiger:name_type": "Rd"}}, {"type": "way", "id": 5378370, "nodes": [38582059, 2578662635, 38316428, 617485447, 38583632, 617485450, 617485451, 38583629], "tags": {"highway": "residential", "name": "Sum View Drive", "tiger:cfcc": "A41", "tiger:county": "Deschutes, OR", "tiger:name_base": "Sumview", "tiger:name_type": "Rd"}}, {"type": "way", "id": 5378701, "nodes": [38502803, 38588381], "tags": {"highway": "residential", "name": "Byram Road", "tiger:cfcc": "A41", "tiger:county": "Deschutes, OR", "tiger:name_base": "Byram", "tiger:name_type": "Ct"}}, {"type": "way", "id": 5378721, "nodes": [38588524, 7643971165, 38588526, 7643971164, 38588528, 7643971163, 38588530, 7643971162, 38466181, 612637187, 7643971161, 612637188, 7643978633, 7643978634, 38588533, 7643978635, 7643978636, 612637189, 7643978637, 612637190, 7643978638, 38178162, 38588537, 612637194, 38588539, 3683292978, 38588541, 3683292979, 38580240], "tags": {"highway": "residential", "name": "Wallace Road", "tiger:cfcc": "A41", "tiger:county": "Deschutes, OR", "tiger:name_base": "Wallace", "tiger:name_type": "Rd"}}, {"type": "way", "id": 48206711, "nodes": [612637163, 612637164, 612637195, 38245922, 612637200, 612637199, 612637198, 612637197, 612637196, 612637205, 612637204, 612637203, 612637201, 3683118931, 38312889, 612637207, 38587488, 3789368177, 3789393535, 38556777], "tags": {"highway": "residential", "name": "Nelson Road", "tiger:cfcc": "A41", "tiger:county": "Deschutes, OR", "tiger:name_base": "Nelson", "tiger:name_type": "Rd"}}, {"type": "way", "id": 48206712, "nodes": [38489407, 612637183, 612637184, 612637185, 38489410, 38489413, 7643975464, 38293229, 38489421, 5618067139, 5618067131, 38489425], "tags": {"highway": "tertiary", "name": "Bear Creek Road", "surface": "paved", "tiger:cfcc": "A41", "tiger:county": "Deschutes, OR", "tiger:name_base": "Bear Creek", "tiger:name_type": "Rd"}}, {"type": "way", "id": 48332558, "nodes": [38287399, 38202103, 614017087, 3251296432, 3251296431, 3251296433, 38495058, 38495060, 4693137406, 38464476, 38495067, 614017085, 38495070, 38495072, 38495075, 3251296447, 38495080, 38386547, 38495083, 4693135830, 38489407, 38495086, 3251308973, 38495088, 38495091, 38312789, 38495093, 612637141, 612637140, 38495096, 38495099, 38354239, 38495102, 38494141, 38495105, 3251308979, 38495109, 4693055820, 38495111, 38495113, 4132081090], "tags": {"NHS": "yes", "hgv": "designated", "hgv:national_network": "yes", "highway": "trunk", "lanes": "2", "maxspeed": "65 mph", "maxspeed:hgv": "60 mph", "name": "Central Oregon Highway", "ref": "US 20", "source:hgv:national_network": "Title 23: Highways Part 658 http://ecfr.gpoaccess.gov/cgi/t/text/text-idx?c=ecfr&rgn=div5&view=text&node=23:1.0.1.7.33&idno=23", "surface": "paved", "tiger:cfcc": "A21", "tiger:county": "Deschutes, OR", "tiger:name_base": "Highway 20", "tiger:name_base_1": "United States Highway 20", "tiger:name_base_2": "Central Oregon", "tiger:name_direction_prefix": "E", "tiger:name_direction_prefix_1": "E", "tiger:name_type_2": "Hwy"}}, {"type": "way", "id": 166553566, "nodes": [38351849, 38518143, 38518144, 38518146, 38518148, 38518151, 38282111, 2578662582, 38518156, 2578662584, 2578662587, 1780025208, 2578662591, 38518158, 2578662589, 1780025207, 2578662585, 38216948, 38518165, 38518166, 38518168, 38296690, 38300200, 38518170, 38518172, 38518179, 38509602, 3683123712, 38518197, 38518204, 38518211, 38518213, 38518215, 38518217, 8719894099, 617485353, 5618281349, 38518219, 38518221, 38518223, 38518225, 8719894041, 8719894038, 38465607], "tags": {"highway": "tertiary", "lanes": "2", "name": "Rickard Road", "surface": "paved", "tiger:cfcc": "A41", "tiger:county": "Deschutes, OR", "tiger:name_base": "Rickard", "tiger:name_type": "Rd", "tiger:reviewed": "no"}}, {"type": "way", "id": 166553619, "nodes": [38489396, 38489397, 38489398, 38489399, 38306796, 38224504, 38489400, 38489401, 38489405, 612637181, 612637182, 3251296448, 612637180, 612637177, 612637178, 612637179, 612637176, 38489407], "tags": {"highway": "tertiary", "lanes": "2", "name": "Bear Creek Road", "tiger:cfcc": "A41", "tiger:county": "Deschutes, OR", "tiger:name_base": "Bear Creek", "tiger:name_type": "Rd", "tiger:reviewed": "no"}}, {"type": "way", "id": 168386393, "nodes": [38533410, 2814834917, 38553299, 2814834911, 2814834909, 38553301, 2814834910, 38553304, 2814834912, 38553306, 617485453, 38553308, 38553309, 38553316, 38553318, 38471235, 38553320, 617485454, 38553321, 38553322, 38549081, 38553323, 38553326, 38296924, 617485379, 617485424, 8720087798, 38553328], "tags": {"highway": "tertiary", "name": "Ward Road", "tiger:cfcc": "A41", "tiger:county": "Deschutes, OR", "tiger:name_base": "Ward", "tiger:name_type": "Rd"}}, {"type": "way", "id": 375574079, "nodes": [38580161, 3789305172, 3683087971, 3789305171, 38580163, 3789305168, 38580165, 3789305142, 3789305135, 3789305126, 38580167, 3683087970, 3683087969, 3789305111, 38580168, 3789305114, 3789305116, 38580170, 3789305113, 3683087968, 3789305108, 38580171, 3789305087, 3789305079, 38580175, 3789305072, 38580177, 3789305071, 38580179, 3789305076, 38580181, 3789305083, 3789305092, 38580183, 3789305107, 3789305110, 38580185, 3683087967, 3789305121, 3789305119, 38279196, 38580189, 3683087966, 38580190, 3683087965, 3789305080, 3683087964, 3789305073, 38580192, 3683087963, 38580194, 3789305066, 3789305063, 3683087962, 3789305054, 38374826, 3789305049, 38580196, 3789305048, 38580197, 38580198, 38580199, 3789305060, 38580200, 3789305090, 38580202, 3683087961, 3789305112, 3789305118, 38580203, 3789305125, 38580205, 3789305147, 3789305152, 3683087960, 3789305155, 3683087959, 3789305153, 3789305143, 38374916, 38580207, 3789305148, 3789305149, 3789305150, 3683087958, 3683087957, 3789305145, 38580209, 3789305139, 3789305136, 38580211, 3789305103, 38580213, 3789305070, 3789305056, 38580215, 3789305022, 38580217, 3789304984, 38580219, 3789304964, 38574493, 3789304950, 38580221, 3789304933, 3789304905, 3789304854, 3683111531, 3789303953, 3789303948, 3789303939, 38580223, 38580225, 3789303926, 3789303924, 38522962, 38580228, 3789303921, 3789303925, 3126235855, 38580230, 3789304760, 3683292973, 3789304773, 38580232, 3683292974, 3683292975, 3683292976, 38224600, 3683292977, 3789303946, 38556745, 3789303944, 38580235, 3789303943, 3789303941, 3789303940, 38394986, 3789379125, 3789303937, 3789303938, 3789303936, 3789303934, 3789303933, 3789303932, 3789303929, 38580238, 38502813, 3789303927, 38580240, 612637192, 3789303930, 38246097, 38474846, 5061165828], "tags": {"highway": "tertiary", "name": "Alfalfa Market Road", "tiger:cfcc": "A41", "tiger:county": "Deschutes, OR", "tiger:name_base": "Alfalfa Market", "tiger:name_type": "Rd"}}, {"type": "way", "id": 856043421, "nodes": [4305127134, 3215346084, 3215346089, 38243053, 38384154, 38384199, 2773174401, 7982212213, 7982212216, 2806813410, 7982212215, 7982212214, 3215346097, 38584201, 7982212218, 7982212217, 3215346098, 7982212219, 2806813409, 7982212223, 7982212222, 3215346099, 7982212221, 7982212220, 7982212224, 38584203, 7982212226, 7982212225, 7982212228, 7982212227, 7982212248, 38584205, 7982212247, 7982212246, 3215346100, 7982212245, 7982212244, 38584207, 7982212253, 7982212251, 7982212252, 2806813408, 7982212250, 7982212249, 7982212241, 7982212243, 7982212242, 38584209, 7982212240, 7982212239, 3215346101, 7982212238, 7982212237, 2806813407, 7982212236, 3215346102, 7982212235, 7982212233, 7982212234, 38584211, 38242540, 38584228, 3215346103, 3215346104, 3202633174, 38584230, 3215346105, 38584232, 38311164, 3202633180, 3202633181, 38584236, 3202633182, 38584238, 3202633183, 3202633184, 38375555, 38584241, 3235694915, 3235694922, 38584242, 2773211704, 38366006, 38584244, 3235694963, 38584246, 3235694984, 38584248, 3202623936, 3202623939, 38195468, 38584250, 3202623938, 3202623937, 38584252, 3202623934, 38584254, 3235694983, 3235694977, 38584256, 3235694958, 38584257, 3235694946, 3235694936, 3235694920, 38584259, 3235694905, 38584261, 3235694896, 3235694894, 3235694893, 38270437, 3202646624, 38584263, 3202646623, 3202646625, 3202646626, 38584265, 3202646630, 38584267, 38302853, 38584270, 38270336, 38500327, 3215353908, 38584277, 2773175101, 38552096, 3199633016, 3199633026, 38583726, 38499492, 3199633182, 3199633196, 38583729, 3199633218, 38528451, 3199633277, 3199633302, 38552799, 38552801, 3199633378, 3199633395, 38552804, 3199633403, 38241368, 3199633406, 3199633408, 38552807, 3199633409, 38552808, 3199633411, 3189669316, 38552811, 3189669315, 3189669314, 38552812, 38182176, 3192969590, 3192969591, 3192969592, 3192969593, 3192969595, 3192969597, 38552817, 3180323651, 38552819, 38397123, 3192969604, 38552822, 38552826, 3192888808, 3192888811, 3192888810, 3199653531, 3192888807, 3192888805, 38552827, 3192888806, 3201107786, 3192888809, 3199653533, 3192888812, 3192888813, 38552829, 3192969615, 3192888814, 3192888815, 3192888817, 3192888818, 3192888820, 38552835, 3192888821, 38552836, 3191221201, 3191221204, 38552838, 3191221212, 3191221218, 3191221223, 38552840, 3191221252, 3191221268, 38552842, 3191221281, 3191221291, 38552843, 3192279882, 38335401, 3192279908, 38335324, 3192279985, 38552850, 3191221381, 3192280115, 3191181639, 38552853, 3191221382, 38552856, 3192280167, 38552858, 1797819802, 3191181702, 3191181729], "tags": {"alt_name": "China Hat Road", "highway": "tertiary", "lanes": "2", "maxspeed": "35 mph", "name": "National Forest Development Road 18", "name_1": "County Highway 18", "name_2": "China Hat Road", "oneway": "no", "ref": "NF 18", "surface": "asphalt", "tiger:cfcc": "A41", "tiger:county": "Deschutes, OR", "tiger:name_base": "Arnold Ice Cave", "tiger:name_base_1": "County Highway 18", "tiger:name_base_2": "China Hat", "tiger:name_type": "Rd", "tiger:name_type_2": "Rd"}}, {"type": "way", "id": 865378203, "nodes": [8066067510, 8066067511, 8066067512, 8066067513, 8066067514, 8066067515, 8066067516, 8066067517, 8066067518, 8066067519, 8066067520, 8066067521, 8066067522, 8066067523, 8066067524], "tags": {"access": "permissive", "highway": "unclassified", "oneway": "no", "surface": "paved"}}]}